Workbook
Name __123Graph_A: #REF!
Name __123Graph_B: #REF!
Name __123Graph_C: #REF!
Name __123Graph_D: #REF!
Name __123Graph_E: #REF!
Name __123Graph_F: #REF!
Name __123Graph_X: #REF!
Name __fa1: {"plansummary",#N/A,FALSE,"PlanSummary";"sales",#N/A,FALSE,"Sales Rec";"productivity",#N/A,FALSE,"Productivity Rec";"capitalspending",#N/A,FALSE,"Capital Spending"}
Name __fa2: {"plansummary",#N/A,FALSE,"PlanSummary";"sales",#N/A,FALSE,"Sales Rec";"productivity",#N/A,FALSE,"Productivity Rec";"capitalspending",#N/A,FALSE,"Capital Spending"}
Name __fa3: {"plansummary",#N/A,FALSE,"PlanSummary";"sales",#N/A,FALSE,"Sales Rec";"productivity",#N/A,FALSE,"Productivity Rec";"capitalspending",#N/A,FALSE,"Capital Spending"}
Name _Dist_Bin: #REF!
Name _Dist_Values: #REF!
Name _fa1: {"plansummary",#N/A,FALSE,"PlanSummary";"sales",#N/A,FALSE,"Sales Rec";"productivity",#N/A,FALSE,"Productivity Rec";"capitalspending",#N/A,FALSE,"Capital Spending"}
Name _fa2: {"plansummary",#N/A,FALSE,"PlanSummary";"sales",#N/A,FALSE,"Sales Rec";"productivity",#N/A,FALSE,"Productivity Rec";"capitalspending",#N/A,FALSE,"Capital Spending"}
Name _fa3: {"plansummary",#N/A,FALSE,"PlanSummary";"sales",#N/A,FALSE,"Sales Rec";"productivity",#N/A,FALSE,"Productivity Rec";"capitalspending",#N/A,FALSE,"Capital Spending"}
Name _Fill: #REF!
Name _Key1: #REF!
Name _Key2: #REF!
Name _Order1: 255
Name _Order2: 255
Name _Regression_X: #REF!
Name _Sort: #REF!
Name _Table1_In1: #REF!
Name _Table1_Out: #REF!
Name a: #REF!
Name abc.doc: {"'Income Statement'!$D$96:$E$101"}
Name ac: #REF!
Name ac: #REF!
Name AS2DocOpenMode: "AS2DocumentEdit"
Name AS2ReportLS: 1
Name AS2StaticLS: #REF!
Name AS2SyncStepLS: 0
Name AS2TickmarkLS: #REF!
Name AS2VersionLS: 300
Name BG_Del: 15
Name BG_Ins: 4
Name BG_Mod: 6
Name Code: #REF!
Name COL: #REF!
Name D: #REF!
Name data1: #REF!
Name data2: #REF!
Name data3: #REF!
Name ÐCompanyName: #REF!
Name Discount: #REF!
Name display_area_2: #REF!
Name ÐYesNoDropdown: #REF!
Name ENGEL: #REF!
Name FCode: #REF!
Name HiddenRows: #REF!
Name HTML_CodePage: 1252
Name HTML_Control: {"'Income Statement'!$D$96:$E$101"}
Name HTML_Description: "Profit & Loss Account"
Name HTML_Email: ""
Name HTML_Header: "Income Statement"
Name HTML_LastUpdate: "6/14/99"
Name HTML_LineAfter: TRUE
Name HTML_LineBefore: TRUE
Name HTML_Name: "Prakash Mishra"
Name HTML_OBDlg2: TRUE

Sheet Pivot
J1: Positions in Upload file
I2: Account
I3: GL Codes
H4: =MID(F4,8,LEN(F4)-7) -> #VALUE! | I4: {=_xludf.XLOOKUP(H4,'Billing sheet'!$CH$3:$CM$3,'Billing sheet'!$CH$2:$CM$2)} -> #NAME?
H5: =MID(F5,8,LEN(F5)-7) -> #VALUE! | I5: {=_xludf.XLOOKUP(H5,'Billing sheet'!$CH$3:$CM$3,'Billing sheet'!$CH$2:$CM$2)} -> #NAME?
H6: =MID(F6,8,LEN(F6)-7) -> #VALUE! | I6: {=_xludf.XLOOKUP(H6,'Billing sheet'!$CH$3:$CM$3,'Billing sheet'!$CH$2:$CM$2)} -> #NAME?
H7: =MID(F7,8,LEN(F7)-7) -> #VALUE! | I7: {=_xludf.XLOOKUP(H7,'Billing sheet'!$CH$3:$CM$3,'Billing sheet'!$CH$2:$CM$2)} -> #NAME?
H8: =MID(F8,8,LEN(F8)-7) -> #VALUE! | I8: {=_xludf.XLOOKUP(H8,'Billing sheet'!$CH$3:$CM$3,'Billing sheet'!$CH$2:$CM$2)} -> #NAME?
H9: =MID(F9,8,LEN(F9)-7) -> #VALUE! | I9: {=_xludf.XLOOKUP(H9,'Billing sheet'!$CH$3:$CM$3,'Billing sheet'!$CH$2:$CM$2)} -> #NAME?
H10: =MID(F10,8,LEN(F10)-7) -> #VALUE! | I10: {=_xludf.XLOOKUP(H10,'Billing sheet'!$CH$3:$CM$3,'Billing sheet'!$CH$2:$CM$2)} -> #NAME?
H11: =MID(F11,8,LEN(F11)-7) -> #VALUE! | I11: {=_xludf.XLOOKUP(H11,'Billing sheet'!$CH$3:$CM$3,'Billing sheet'!$CH$2:$CM$2)} -> #NAME?
H12: =MID(F12,8,LEN(F12)-7) -> #VALUE! | I12: {=_xludf.XLOOKUP(H12,'Billing sheet'!$CH$3:$CM$3,'Billing sheet'!$CH$2:$CM$2)} -> #NAME?
H13: =MID(F13,8,LEN(F13)-7) -> #VALUE! | I13: {=_xludf.XLOOKUP(H13,'Billing sheet'!$CH$3:$CM$3,'Billing sheet'!$CH$2:$CM$2)} -> #NAME?
H14: =MID(F14,8,LEN(F14)-7) -> #VALUE! | I14: {=_xludf.XLOOKUP(H14,'Billing sheet'!$CH$3:$CM$3,'Billing sheet'!$CH$2:$CM$2)} -> #NAME?
H15: =MID(F15,8,LEN(F15)-7) -> #VALUE! | I15: {=_xludf.XLOOKUP(H15,'Billing sheet'!$CH$3:$CM$3,'Billing sheet'!$CH$2:$CM$2)} -> #NAME?
... H8079: =MID(F8079,8,LEN(F8079)-7) -> #VALUE! | I8079: {=_xludf.XLOOKUP(H8079,'Billing sheet'!$CH$3:$CM$3,'Billing sheet'!$CH$2:$CM$2)} -> #NAME?
A8156: Billable Cost2 | B8156: Billable Cost
A8158: Invoice No. | B8158: Inv/ Bill No. | C8158: IC Code | D8158: Sum of Billable Cost
A8159: 30001333 | B8159: ATS/000250/25 | C8159: IN_RSM_GBS | D8159: 3475.27 | G8159: =D8159 -> 3475.27
A8160: 30001333 | B8160: ATS/000583/25 | C8160: IN_RSM_GBS | D8160: 3475.27 | G8160: =D8160 -> 3475.27
A8161: 30001333 | B8161: ATS/000914/25 | C8161: IN_RSM_GBS | D8161: 3475.27 | G8161: =D8161 -> 3475.27
A8162: 30001333 | B8162: ATS/001244/25 | C8162: IN_RSM_GBS | D8162: 3475.27 | G8162: =D8162 -> 3475.27
A8163: 30001333 | B8163: PGPLTGFEB1512526 | C8163: IN_RSM_GBS | D8163: 143514.19 | G8163: =D8163 -> 143514.19
A8164: 30001333 | B8164: PGPLTGFEB1502526 | C8164: IN_RSM_GBS | D8164: 137673.48 | G8164: =D8164 -> 137673.48
A8165: 30001333 | B8165: PGPLTGFEB1492526 | C8165: IN_RSM_GBS | D8165: 139163.1 | G8165: =D8165 -> 139163.1
A8166: 30001333 | B8166: CA1280002854 | C8166: IN_RSM_GBS | D8166: 20000 | G8166: =D8166 -> 20000
A8167: 30001333 | B8167: CD1210201355 | C8167: IN_RSM_GBS | D8167: 230467 | G8167: =D8167 -> 230467
A8168: 30001333 | B8168: CD1210201375 | C8168: IN_RSM_GBS | D8168: 9214 | G8168: =D8168 -> 9214
A8169: 30001333 | B8169: CA1280002827 | C8169: IN_RSM_GBS | D8169: 720.34 | G8169: =D8169 -> 720.34
A8170: 30001333 | B8170: 20258766 | C8170: IN_RSM_GBS | D8170: 3300 | G8170: =D8170 -> 3300
... A8181: 30001317 | B8181: RT95069628 | C8181: IN_MFM_L | D8181: 360000 | G8181: =D8181 -> 360000

Sheet Billing sheet
CC1: to be provided by Business team | CH1: GL Codes
O2: Recharge General Cost - Payroll | Q2: Recharge General Cost - Payroll | R2: Recharge General Cost - Retirals | S2: Recharge General Cost - Retirals | T2: Recharge General Cost - Payroll | U2: Recharge General Cost - Payroll | V2: Recharge General Cost - Payroll | W2: Recharge General Cost - Payroll | X2: Recharge General Cost - Payroll | Z2: Recharge General Cost - Leadership cost | AA2: Recharge General Cost - Manager | AC2: Recharge General Cost - Manager | AD2: Recharge General Cost - Manager | AE2: Recharge General Cost - Manager | AI2: Mark up | AJ2: Recharge General Cost - Desk Cost | AK2: Mark up | AW2: Data CC | AX2: Data CC | AY2: Data CC | AZ2: Data CC | BA2: Data CC | CC2: Ref Key 1 | CE2: Assignment Number (20) & Reference | CF2: Ref Key 3 | CG2: Ref Key 2 | CH2: 742234 | CI2: 742238 | CJ2: =CH2+1 -> 742235 | CK2: =CJ2+1 -> 742236 | CL2: =CK2+1 -> 742237 | CM2: 842028
A3: Workday ID | B3: EmpNo | C3: Name | D3: Date of joining | E3: Last working day | F3: Grade | G3: Capability Center | H3: ELT | I3: Location | J3: Type | K3: Billing | L3: Category of Billing | M3: Markup % | N3: Billing days | O3: Fixed CTC | P3: % of Bonus | Q3: Bonus 2026 | R3: Gratuity | S3: Leave Encashment | T3: PF admin Monthly | U3: EDLI Monthly | V3: Commision/ Joining bonus | W3: SBP Accrual | X3: Insurance | Y3: Total Payroll | Z3: Leadership cost | AA3: Managers desk fee | AB3: Payroll excluding Manager cost | AC3: Shiv Shankar's Cost | AD3: Anusha' Cost | AE3: Manager cost | AF3: Manager | AG3: Manager ID | AH3: Total Cost other than desk cost | AI3: TP on total cost | AJ3: Gross Desk Cost | AK3: TP on desk cost | AL3: Total billable amount | AM3: Client | AN3: Client for sumifs | AO3: Cost center | AP3: Legal Entity | AQ3: Classification | AR3: FTE count | AS3: Comments | AV3: Managers | AW3: Service Area | AX3: LOB | AY3: BU | AZ3: Cost center | BA3: Client | BB3: ** | BC3: LOP | BD3: Working_days | BE3: Days_Worked | BF3: NJoinee_ArrDays | BG3: Prv_Adj_Days | BH3: Prv_Arrear_Days | BI3: Billing days | BJ3: LOP | BK3: C/F LOP | BL3: Prv_Adj_Days | BM3: Billing adj | BN3: Closing LOP | BO3: LOP -1 month | BP3: LOP -2 Month | BQ3: LOP -3 Month | BR3: LOP -4 Month | BS3: LOP -5 Month | BT3: LOP -6 Month | BU3: LOP -7 Month | BV3: LOP -8 Month | BW3: LOP -9 Month | BX3: LOP -10 Month | BY3: LOP -11 Month | BZ3: Check | CB3: Billed/ Unbilled | CC3: IC Code | CD3: Customer Code | CE3: Invoice No. | CF3: EmpNo | CG3: Capability Center | CH3: Recharge General Cost - Payroll | CI3: Recharge General Cost - Manager | CJ3: Recharge General Cost - Leadership cost | CK3: Recharge General Cost - Desk Cost | CL3: Recharge General Cost - Retirals | CM3: Mark up | CO3: Diff
A4: W0008891 | B4: GCC5670 | C4: Yashwanth J | D4: 45978 | F4: L07 | G4: Finance Capability Center | H4: Abhishek Khurana | I4: IN - Hyderabad_HQ | K4: Unique | L4: Active | M4: 0.085 | N4: 28 | O4: 114840 | R4: 2760.5769 | S4: 1595 | T4: 287.1 | U4: 75 | W4: 0 | X4: 4460.3751 | Y4: 124018.05 | Z4: 5687.5 | AB4: 129705.55 | AH4: 129705.55 | AI4: 11024.972 | AJ4: 29700 | AK4: 2524.5 | AL4: 172955.02 | AM4: Randstad NV | AN4: Randstad NV | AO4: 1005310 | AP4: Randstad NV | AQ4: Billable | AR4: 1 | AW4: Talent Onboarding Solutions | AX4: GFKS | AY4: RGCC FSSC | AZ4: 1005310 | BC4: Considered | CB4: Accruals | CC4: NL_RSH | CD4: 60006 | CE4: #N/A | CF4: =A4 -> W0008891 | CG4: =G4 -> Finance Capability Center | CH4: =SUM(O4,Q4,T4:X4,) -> 119662.48 | CI4: =SUM(AA4,AE4) -> 0 | CJ4: =SUM(Z4) -> 5687.5 | CK4: =AJ4 -> 29700 | CL4: =SUM(R4:S4) -> 4355.5769 | CM4: =SUM(AI4,AK4) -> 13549.472 | CO4: =SUM(CH4:CM4,-AL4) -> 0
A5: W0005462 | B5: GCC4787 | C5: Namrata Gupta | D5: 45427 | F5: L05 | G5: BRAF | H5: Daco Team | I5: IN - Bangalore_HQ | K5: Unique | L5: Active | M5: 0.085 | N5: 28 | O5: 406333.33 | P5: 0.15 | Q5: 60950 | R5: 9767.6282 | S5: 5643.5185 | T5: 1015.8333 | U5: 75 | W5: 0 | X5: 5460.3751 | Y5: 489245.69 | Z5: 0 | AB5: 489245.69 | AH5: 489245.69 | AI5: 41585.884 | AJ5: 29700 | AK5: 2524.5 | AL5: 563056.07 | AM5: Randstad NV | AN5: Randstad NV | AO5: 1005220 | AP5: Randstad NV | AQ5: Billable | AR5: 1 | AW5: 0 | AX5: GFKS | AY5: 0 | AZ5: 1005220 | BC5: Considered | CB5: Accruals | CC5: NL_RSH | CD5: 60006 | CE5: #N/A | CF5: =A5 -> W0005462 | CG5: =G5 -> BRAF | CH5: =SUM(O5,Q5,T5:X5,) -> 473834.54 | CI5: =SUM(AA5,AE5) -> 0 | CJ5: =SUM(Z5) -> 0 | CK5: =AJ5 -> 29700 | CL5: =SUM(R5:S5) -> 15411.147 | CM5: =SUM(AI5,AK5) -> 44110.384 | CO5: =SUM(CH5:CM5,-AL5) -> 0
A6: W0005463 | B6: GCC4788 | C6: Kavitha Gunaseelan | D6: 45446 | F6: L04 | G6: BRAF | H6: Daco Team | I6: IN - Bangalore_HQ | K6: Unique | L6: Active | M6: 0.085 | N6: 28 | O6: 410166.67 | P6: 0.15 | Q6: 61525 | R6: 9859.7756 | S6: 5696.7593 | T6: 1025.4167 | U6: 75 | W6: 0 | X6: 5460.3751 | Y6: 493808.99 | Z6: 0 | AB6: 493808.99 | AH6: 493808.99 | AI6: 41973.764 | AJ6: 29700 | AK6: 2524.5 | AL6: 568007.26 | AM6: Randstad NV | AN6: Randstad NV | AO6: 1005220 | AP6: Randstad NV | AQ6: Billable | AR6: 1 | AW6: 0 | AX6: GFKS | AY6: 0 | AZ6: 1005220 | BC6: Considered | CB6: Accruals | CC6: NL_RSH | CD6: 60006 | CE6: #N/A | CF6: =A6 -> W0005463 | CG6: =G6 -> BRAF | CH6: =SUM(O6,Q6,T6:X6,) -> 478252.46 | CI6: =SUM(AA6,AE6) -> 0 | CJ6: =SUM(Z6) -> 0 | CK6: =AJ6 -> 29700 | CL6: =SUM(R6:S6) -> 15556.535 | CM6: =SUM(AI6,AK6) -> 44498.264 | CO6: =SUM(CH6:CM6,-AL6) -> 0
A7: W0005464 | B7: GCC4789 | C7: Rahul Kedia | D7: 45406 | F7: L04 | G7: BRAF | H7: Daco Team | I7: IN - Bangalore_HQ | K7: Unique | L7: Active | M7: 0.085 | N7: 28 | O7: 456000 | P7: 0.15 | Q7: 68400 | R7: 10961.538 | S7: 6333.3333 | T7: 1140 | U7: 75 | W7: 45076.596 | X7: 5460.3751 | Y7: 593446.84 | Z7: 0 | AB7: 593446.84 | AH7: 593446.84 | AI7: 50442.982 | AJ7: 29700 | AK7: 2524.5 | AL7: 676114.32 | AM7: Randstad NV | AN7: Randstad NV | AO7: 1005220 | AP7: Randstad NV | AQ7: Billable | AR7: 1 | AW7: 0 | AX7: GFKS | AY7: 0 | AZ7: 1005220 | BC7: Considered | CB7: Accruals | CC7: NL_RSH | CD7: 60006 | CE7: #N/A | CF7: =A7 -> W0005464 | CG7: =G7 -> BRAF | CH7: =SUM(O7,Q7,T7:X7,) -> 576151.97 | CI7: =SUM(AA7,AE7) -> 0 | CJ7: =SUM(Z7) -> 0 | CK7: =AJ7 -> 29700 | CL7: =SUM(R7:S7) -> 17294.872 | CM7: =SUM(AI7,AK7) -> 52967.482 | CO7: =SUM(CH7:CM7,-AL7) -> 0
A8: W0005465 | B8: GCC4790 | C8: Rohit Garg | D8: 45434 | F8: L06 | G8: BRAF | H8: Daco Team | I8: IN - Bangalore_HQ | K8: Unique | L8: Active | M8: 0.085 | N8: 28 | O8: 335666.67 | P8: 0.18 | Q8: 60420 | R8: 8068.9103 | S8: 4662.037 | T8: 839.16667 | U8: 75 | W8: 0 | X8: 4460.3751 | Y8: 414192.16 | Z8: 0 | AB8: 414192.16 | AH8: 414192.16 | AI8: 35206.333 | AJ8: 29700 | AK8: 2524.5 | AL8: 481622.99 | AM8: Randstad NV | AN8: Randstad NV | AO8: 1005220 | AP8: Randstad NV | AQ8: Billable | AR8: 1 | AW8: 0 | AX8: GFKS | AY8: 0 | AZ8: 1005220 | BC8: Considered | CB8: Accruals | CC8: NL_RSH | CD8: 60006 | CE8: #N/A | CF8: =A8 -> W0005465 | CG8: =G8 -> BRAF | CH8: =SUM(O8,Q8,T8:X8,) -> 401461.21 | CI8: =SUM(AA8,AE8) -> 0 | CJ8: =SUM(Z8) -> 0 | CK8: =AJ8 -> 29700 | CL8: =SUM(R8:S8) -> 12730.947 | CM8: =SUM(AI8,AK8) -> 37730.833 | CO8: =SUM(CH8:CM8,-AL8) -> 0
A9: W0005466 | B9: GCC4792 | C9: Devi Haridas | D9: 45460 | F9: L03 | G9: BRAF | H9: Daco Team | I9: IN - Bangalore_HQ | K9: Unique | L9: Active | M9: 0.085 | N9: 28 | O9: 700625 | P9: 0.15 | Q9: 105093.75 | R9: 16841.947 | S9: 9730.9028 | T9: 1751.5625 | U9: 75 | W9: 0 | X9: 5460.3751 | Y9: 839578.54 | Z9: 0 | AB9: 839578.54 | AH9: 839578.54 | AI9: 71364.176 | AJ9: 29700 | AK9: 2524.5 | AL9: 943167.21 | AM9: Randstad NV | AN9: Randstad NV | AO9: 1005220 | AP9: Randstad NV | AQ9: Billable | AR9: 1 | AW9: 0 | AX9: GFKS | AY9: Randstad Inhouse Netherlands | AZ9: 1005220 | BC9: Considered | CB9: Accruals | CC9: NL_RSH | CD9: 60006 | CE9: #N/A | CF9: =A9 -> W0005466 | CG9: =G9 -> BRAF | CH9: =SUM(O9,Q9,T9:X9,) -> 813005.69 | CI9: =SUM(AA9,AE9) -> 0 | CJ9: =SUM(Z9) -> 0 | CK9: =AJ9 -> 29700 | CL9: =SUM(R9:S9) -> 26572.85 | CM9: =SUM(AI9,AK9) -> 73888.676 | CO9: =SUM(CH9:CM9,-AL9) -> 0
A10: W0005467 | B10: GCC5492 | C10: Kaaviya Murali | D10: 45838 | F10: L05 | G10: BRAF | H10: Daco team | I10: IN - Bangalore_HQ | K10: Unique | L10: Active | M10: 0.085 | N10: 28 | O10: 303660 | P10: 0.15 | Q10: 45549 | R10: 7299.5192 | S10: 4217.5 | T10: 759.15 | U10: 75 | W10: 0 | X10: 5460.3751 | Y10: 367020.54 | Z10: 0 | AB10: 367020.54 | AH10: 367020.54 | AI10: 31196.746 | AJ10: 29700 | AK10: 2524.5 | AL10: 430441.79 | AM10: Randstad NV | AN10: Randstad NV | AO10: 1005220 | AP10: Randstad NV | AQ10: Billable | AR10: 1 | AW10: BRAF | AX10: RGCC HQ | AY10: BRAF | AZ10: 1005220 | BC10: Considered | CB10: Accruals | CC10: NL_RSH | CD10: 60006 | CE10: #N/A | CF10: =A10 -> W0005467 | CG10: =G10 -> BRAF | CH10: =SUM(O10,Q10,T10:X10,) -> 355503.53 | CI10: =SUM(AA10,AE10) -> 0 | CJ10: =SUM(Z10) -> 0 | CK10: =AJ10 -> 29700 | CL10: =SUM(R10:S10) -> 11517.019 | CM10: =SUM(AI10,AK10) -> 33721.246 | CO10: =SUM(CH10:CM10,-AL10) -> 0
A11: W0004060 | B11: GCC0008 | C11: Thejasvi Potta | D11: 40259 | F11: L08 | G11: HR Capability Center | H11: Shail Dasika | I11: IN - Hyderabad_HQ | K11: Unique | L11: Active | M11: 0.05 | N11: 28 | O11: 101126.58 | R11: 2430.9295 | S11: 1228.9699 | T11: 252.81667 | U11: 75 | W11: 0 | X11: 5460.3751 | Y11: 110574.67 | Z11: 12402.5 | AB11: 122977.17 | AE11: 33281 | AF11: Arpan Roy / Saurab | AG11: GCC5445 | AH11: 156258.17 | AI11: 7812.9087 | AJ11: 29700 | AK11: 1485 | AL11: 195256.08 | AM11: RUS | AN11: RUS | AO11: 35880 | AP11: Randstad Professional US LP, | AQ11: Billable | AR11: 1 | AW11: Sourcing | AX11: HRCC | AY11: HRCC | AZ11: 35880 | BC11: Considered | CB11: Billed | CC11: US_SAP_L | CD11: 60002 | CE11: 30001312 | CF11: =A11 -> W0004060 | CG11: HR | CH11: =SUM(O11,Q11,T11:X11,) -> 106914.78 | CI11: =SUM(AA11,AC11:AE11) -> 33281 | CJ11: =SUM(Z11) -> 12402.5 | CK11: =AJ11 -> 29700 | CL11: =SUM(R11:S11) -> 3659.8994 | CM11: =SUM(AI11,AK11) -> 9297.9087 | CO11: =SUM(CH11:CM11,-AL11) -> 0
A12: W0004061 | B12: GCC0044 | C12: Sunil Tangelapally | D12: 41699 | F12: L06 | G12: Talent Services Capability Center | H12: Ankur Sud | I12: IN - Hyderabad_HQ | K12: Unique | L12: Active | M12: 0.05 | N12: 28 | O12: 143905.42 | R12: 3339.0745 | S12: 1929.2431 | T12: 347.26375 | U12: 75 | W12: 0 | X12: 4460.3751 | Y12: 154056.37 | Z12: 4154.1667 | AB12: 158210.54 | AH12: 158210.54 | AI12: 7910.527 | AJ12: 29700 | AK12: 1485 | AL12: 197306.07 | AM12: Canada | AN12: Canada | AO12: 5151 38% + 2692 8% + 2653 15% + 2670 8% + 5436 8% + 2633 23% | AP12: Randstad Interim Inc. | AQ12: Billable | AR12: 1 | AW12: Recruiting(KR) | AX12: CANADA | AY12: PTS CDN RCD | AZ12: 5151 38% + 2692 8% + 2653 15% + 2670 8% + 5436 8% + 2633 23% | BC12: Considered | CB12: Billed | CC12: CA_RIC_SAP | CD12: 60005 | CE12: 30001334 | CF12: =A12 -> W0004061 | CG12: TS | CH12: =SUM(O12,Q12,T12:X12,) -> 148788.06 | CI12: =SUM(AA12,AC12:AE12) -> 0 | CJ12: =SUM(Z12) -> 4154.1667 | CK12: =AJ12 -> 29700 | CL12: =SUM(R12:S12) -> 5268.3176 | CM12: =SUM(AI12,AK12) -> 9395.527 | CO12: =SUM(CH12:CM12,-AL12) -> 0
A13: W0004062 | B13: GCC0048 | C13: Vaibhav Gupta | D13: 41750 | F13: L04 | G13: Talent Services Capability Center | H13: Ankur Sud | I13: IN - Hyderabad_HQ | K13: Unique | L13: Active | M13: 0.05 | N13: 28 | O13: 324424.67 | P13: 0.15 | Q13: 48663.7 | R13: 7678.4776 | S13: 0 | T13: 798.56167 | U13: 75 | W13: 8195.7448 | X13: 5460.3751 | Y13: 395296.53 | Z13: 4154.1667 | AB13: 399450.69 | AH13: 399450.69 | AI13: 19972.535 | AJ13: 29700 | AK13: 1485 | AL13: 450608.23 | AM13: RUS | AN13: RUS | AO13: 35801 | AP13: Randstad Professional US LP, | AQ13: Billable | AR13: 1 | AW13: Leadership | AX13: RD US | AY13: RGCC RD US | AZ13: 35801 | BC13: Considered | CB13: Billed | CC13: US_SAP_L | CD13: 60002 | CE13: 30001312 | CF13: =A13 -> W0004062 | CG13: TS | CH13: =SUM(O13,Q13,T13:X13,) -> 387618.05 | CI13: =SUM(AA13,AC13:AE13) -> 0 | CJ13: =SUM(Z13) -> 4154.1667 | CK13: =AJ13 -> 29700 | CL13: =SUM(R13:S13) -> 7678.4776 | CM13: =SUM(AI13,AK13) -> 21457.535 | CO13: =SUM(CH13:CM13,-AL13) -> 0
A14: W0004063 | B14: GCC0049 | C14: Shashank Gundu | D14: 41760 | F14: L05 | G14: Talent Services Capability Center | H14: Ankur Sud | I14: IN - Hyderabad_HQ | K14: Unique | L14: Active | M14: 0.05 | N14: 28 | O14: 212728.25 | Q14: 0 | R14: 4993.4696 | S14: 0 | T14: 519.32083 | U14: 75 | W14: 8195.7448 | X14: 4460.3751 | Y14: 230972.16 | Z14: 4154.1667 | AB14: 235126.33 | AH14: 235126.33 | AI14: 11756.316 | AJ14: 29700 | AK14: 1485 | AL14: 278067.64 | AM14: RUS | AN14: RUS | AO14: 35879 | AP14: Randstad Professional US LP, | AQ14: Billable | AR14: 1 | AW14: Leadership | AX14: RD US | AY14: Digital US - ConRtl | AZ14: 35879 | BC14: Considered | CB14: Billed | CC14: US_SAP_L | CD14: 60002 | CE14: 30001312 | CF14: =A14 -> W0004063 | CG14: TS | CH14: =SUM(O14,Q14,T14:X14,) -> 225978.69 | CI14: =SUM(AA14,AC14:AE14) -> 0 | CJ14: =SUM(Z14) -> 4154.1667 | CK14: =AJ14 -> 29700 | CL14: =SUM(R14:S14) -> 4993.4696 | CM14: =SUM(AI14,AK14) -> 13241.316 | CO14: =SUM(CH14:CM14,-AL14) -> 0
A15: W0004064 | B15: GCC0096 | C15: Praveen Sukkala | D15: 42051 | F15: L11 | G15: Talent Services Capability Center | H15: Ankur Sud | I15: IN - Hyderabad_HQ | K15: Unique | L15: Active | M15: 0.05 | N15: 28 | O15: 72550.167 | R15: 1743.9944 | S15: 125.95515 | T15: 181.37542 | U15: 75 | W15: 0 | X15: 4460.3751 | Y15: 79136.867 | Z15: 4154.1667 | AB15: 83291.033 | AH15: 83291.033 | AI15: 4164.5517 | AJ15: 29700 | AK15: 1485 | AL15: 118640.59 | AM15: Randstad Business solutions Ltd | AN15: Randstad Business solutions Ltd -Digital | AO15: B5500_OFFSH | AP15: Randstad Solutions Limited | AQ15: Billable | AR15: 1 | AW15: Recruiting(KR) | AX15: Randstad UK | AY15: RGCC RD UK | AZ15: B5500_OFFSH | BC15: Considered | CB15: Billed | CC15: UK_REB_L | CD15: 60009 | CE15: 30001337 | CF15: =A15 -> W0004064 | CG15: TS | CH15: =SUM(O15,Q15,T15:X15,) -> 77266.917 | CI15: =SUM(AA15,AC15:AE15) -> 0 | CJ15: =SUM(Z15) -> 4154.1667 | CK15: =AJ15 -> 29700 | CL15: =SUM(R15:S15) -> 1869.9495 | CM15: =SUM(AI15,AK15) -> 5649.5517 | CO15: =SUM(CH15:CM15,-AL15) -> 0
A16: W0004065 | B16: GCC0113 | C16: Sandeep Ejanthkar Ashok | D16: 42107 | E16: 46066 | F16: L09 | G16: Finance Capability Center | H16: Abhishek Khurana | I16: IN - Hyderabad_HQ | K16: Unique | L16: Exit emp | M16: 0.085 | N16: 13 | O16: 50655.622 | P16: 0.1 | Q16: 5065.5622 | R16: 2622.7043 | S16: 0 | T16: 272.76125 | U16: 75 | W16: 9220.2129 | X16: 4460.3751 | Y16: 72372.238 | Z16: 5687.5 | AB16: 78059.738 | AH16: 78059.738 | AI16: 6635.0777 | AJ16: 29700 | AK16: 2524.5 | AL16: 116919.32 | AM16: RGCC HQ | AN16: RGCC Hyd | AO16: RGCC-HQ | AP16: RGCC Hyd | AQ16: Non Billable | AR16: 1 | AW16: Data Analytics | AX16: RGCC HQ | AY16: RGCC HQ | AZ16: RGCC-HQ | BC16: Considered | CB16: Unbillled
A17: W0004067 | B17: GCC0120 | C17: Kishore Banda | D17: 42114 | F17: L09 | G17: Talent Services Capability Center | H17: Ankur Sud | I17: IN - Hyderabad_HQ | K17: Unique | L17: Active | M17: 0.05 | N17: 28 | O17: 100392.08 | R17: 2293.0809 | S17: 298.10052 | T17: 238.48042 | U17: 75 | W17: 6146.8086 | X17: 4460.3751 | Y17: 113903.93 | Z17: 4154.1667 | AB17: 118058.1 | AH17: 118058.1 | AI17: 5902.9048 | AJ17: 29700 | AK17: 1485 | AL17: 155146 | AM17: RUS | AN17: RUS | AO17: 35875 | AP17: Randstad Professional US LP, | AQ17: Billable | AR17: 1 | AW17: Recruiting(KR) | AX17: RD US | AY17: Digital US - BFSI | AZ17: 35875 | BC17: Considered | CB17: Billed | CC17: US_SAP_L | CD17: 60002 | CE17: 30001312 | CF17: =A17 -> W0004067 | CG17: TS | CH17: =SUM(O17,Q17,T17:X17,) -> 111312.75 | CI17: =SUM(AA17,AC17:AE17) -> 0 | CJ17: =SUM(Z17) -> 4154.1667 | CK17: =AJ17 -> 29700 | CL17: =SUM(R17:S17) -> 2591.1815 | CM17: =SUM(AI17,AK17) -> 7387.9048 | CO17: =SUM(CH17:CM17,-AL17) -> 0
A18: W0004068 | B18: GCC0170 | C18: Vaishnavi Kolluru | D18: 42261 | F18: L10 | G18: HR Capability Center | H18: Shail Dasika | I18: IN - Hyderabad_HQ | K18: Unique | L18: Active | M18: 0.05 | N18: 28 | O18: 66747.583 | R18: 1604.5112 | S18: 463.52546 | T18: 166.86917 | U18: 75 | W18: 2048.9362 | X18: 4460.3751 | Y18: 75566.801 | Z18: 12402.5 | AB18: 87969.301 | AE18: 33281 | AF18: Arpan Roy / Saurab | AG18: GCC5445 | AH18: 121250.3 | AI18: 6062.515 | AJ18: 29700 | AK18: 1485 | AL18: 158497.82 | AM18: RUS | AN18: RUS | AO18: 90208 | AP18: Randstad Professional US LP, | AQ18: Billable | AR18: 1 | AW18: Sourcing | AX18: HRCC | AY18: HRCC | AZ18: 90208 | BC18: Considered | CB18: Billed | CC18: US_SAP_L | CD18: 60002 | CE18: 30001312 | CF18: =A18 -> W0004068 | CG18: HR | CH18: =SUM(O18,Q18,T18:X18,) -> 73498.764 | CI18: =SUM(AA18,AC18:AE18) -> 33281 | CJ18: =SUM(Z18) -> 12402.5 | CK18: =AJ18 -> 29700 | CL18: =SUM(R18:S18) -> 2068.0367 | CM18: =SUM(AI18,AK18) -> 7547.515 | CO18: =SUM(CH18:CM18,-AL18) -> 0
A19: W0004069 | B19: GCC0204 | C19: Praveen Pallerlamudi | D19: 42361 | F19: L04 | G19: Talent Services Capability Center | H19: Aqueel Merchant | I19: IN - Hyderabad_HQ | K19: Managers | L19: Active | M19: 0.05 | N19: 28 | O19: 425053.92 | P19: 0.22 | Q19: 93511.862 | R19: 10217.644 | S19: 0 | T19: 1062.635 | U19: 75 | W19: 28685.107 | X19: 5460.3751 | Y19: 564066.54 | Z19: 4154.1667 | AA19: 29700 | AB19: 597920.71 | AE19: -597920.71 | AH19: 0 | AI19: 0 | AK19: 0 | AL19: 0 | AM19: Randstad Business solutions Ltd +Randstad Business solutions Ltd + Randstad Business solutions Ltd + Randstad Business solutions Ltd + Pareto Law UK Limited + RUS + RUS + RUS + RUS + Canada + Canada + RGCC Australia + RGCC Australia + RGCC Australia + Randstad Inhouse Netherland + Yacht Netherlands + Tempo Netherlands + Tempo Netherlands | AN19: Managers cost | AO19: P1000_OFFSH 8% + C9000_OFFSH 8% + D9503_OFFSH 8% + E9000_OFFSH 8% + CSEX_OFFSH 8% + 35801 31% + 38542 4% + 12021 4% + 19449 4% + 5151 5% + 2933 5% + 5185 1% + 7826 0.5% + 7071 0.5% + 7178485 2% + 1951 1% + 1502348 RRC TTPM 1% + 150149556G1495 1% | AP19: RGCC Hyd | AQ19: Non Billable -Managers | AR19: 1 | AW19: Leadership | AX19: RT | AY19: RGCC RT East | AZ19: P1000_OFFSH 8% + C9000_OFFSH 8% + D9503_OFFSH 8% + E9000_OFFSH 8% + CSEX_OFFSH 8% + 35801 31% + 38542 4% + 12021 4% + 19449 4% + 5151 5% + 2933 5% + 5185 1% + 7826 0.5% + 7071 0.5% + 7178485 2% + 1951 1% + 1502348 RRC TTPM 1% + 150149556G1495 1% | BC19: Considered | CB19: Unbillled
A20: W0004070 | B20: GCC0233 | C20: Purna S | D20: 42500 | F20: L09 | G20: Enablers-GCC | H20: Aqueel Merchant | I20: IN - Hyderabad_HQ | K20: Unique | L20: Active | M20: 0 | N20: 28 | O20: 101403.5 | P20: 0.1 | Q20: 10140.35 | R20: 2437.5841 | S20: 316.88594 | T20: 253.50875 | U20: 75 | W20: 8099.4448 | X20: 4460.3751 | Y20: 127186.65 | Z20: 0 | AB20: 127186.65 | AH20: 127186.65 | AI20: 0 | AJ20: 29700 | AK20: 0 | AL20: 156886.65 | AM20: RGCC HQ | AN20: RGCC Hyd | AO20: RGCC-HQ | AP20: RGCC Hyd | AQ20: Non Billable | AR20: 1 | AW20: Internal Communication | AX20: RGCC HQ | AY20: RGCC HQ | AZ20: RGCC-HQ | BC20: Considered | CB20: Unbillled
A21: W0004071 | B21: GCC0234 | C21: Sri Harsha Satyavaram | D21: 42501 | F21: L07 | G21: Talent Services Capability Center | H21: Ankur Sud | I21: IN - Hyderabad_HQ | K21: Unique | L21: Active | M21: 0.05 | N21: 28 | O21: 155968.58 | R21: 3629.0545 | S21: 0 | T21: 377.42167 | U21: 75 | W21: 0 | X21: 4460.3751 | Y21: 164510.43 | Z21: 4154.1667 | AB21: 168664.6 | AH21: 168664.6 | AI21: 8433.2301 | AJ21: 29700 | AK21: 1485 | AL21: 208282.83 | AM21: RUS | AN21: RUS | AO21: 35070 | AP21: Randstad Professional US LP, | AQ21: Billable | AR21: 1 | AW21: Operations | AX21: RD US | AY21: Digital US - RITS - TPV | AZ21: 35070 | BC21: Considered | CB21: Billed | CC21: US_SAP_L | CD21: 60002 | CE21: 30001312 | CF21: =A21 -> W0004071 | CG21: TS | CH21: =SUM(O21,Q21,T21:X21,) -> 160881.38 | CI21: =SUM(AA21,AC21:AE21) -> 0 | CJ21: =SUM(Z21) -> 4154.1667 | CK21: =AJ21 -> 29700 | CL21: =SUM(R21:S21) -> 3629.0545 | CM21: =SUM(AI21,AK21) -> 9918.2301 | CO21: =SUM(CH21:CM21,-AL21) -> 0
A22: W0005123 | B22: GCC0317 | C22: Venkata Kishore G.K. | D22: 42730 | F22: L07 | G22: Talent Services Capability Center | H22: Ankur Sud | I22: IN - Hyderabad_HQ | K22: Unique | L22: Active | M22: 0.05 | N22: 28 | O22: 113340.17 | R22: 2604.3309 | S22: 1090.9253 | T22: 270.85042 | U22: 75 | W22: 10433.183 | X22: 4460.3751 | Y22: 132274.83 | Z22: 4154.1667 | AB22: 136429 | AH22: 136429 | AI22: 6821.4499 | AJ22: 29700 | AK22: 1485 | AL22: 174435.45 | AM22: RUS | AN22: RUS | AO22: 34732 | AP22: Randstad Professional US LP, | AQ22: Billable | AR22: 1 | AW22: Leadership | AX22: RE | AY22: RGCC OTS US ENG | AZ22: 34732 | BC22: Considered | CB22: Billed | CC22: US_SAP_L | CD22: 60002 | CE22: 30001312 | CF22: =A22 -> W0005123 | CG22: TS | CH22: =SUM(O22,Q22,T22:X22,) -> 128579.58 | CI22: =SUM(AA22,AC22:AE22) -> 0 | CJ22: =SUM(Z22) -> 4154.1667 | CK22: =AJ22 -> 29700 | CL22: =SUM(R22:S22) -> 3695.2562 | CM22: =SUM(AI22,AK22) -> 8306.4499 | CO22: =SUM(CH22:CM22,-AL22) -> 0
A23: W0004072 | B23: GCC0331 | C23: Sinduja Kola | D23: 42758 | F23: L11 | G23: HR Capability Center | H23: Shail Dasika | I23: IN - Hyderabad_HQ | K23: Unique | L23: Active | M23: 0.05 | N23: 28 | O23: 54167.583 | R23: 1302.1074 | S23: 752.3287 | T23: 135.41917 | U23: 75 | W23: 5548.5192 | X23: 4460.3751 | Y23: 66441.333 | Z23: 12402.5 | AB23: 78843.833 | AH23: 78843.833 | AI23: 3942.1916 | AJ23: 29700 | AK23: 1485 | AL23: 113971.02 | AM23: RUS | AN23: RUS | AO23: 90208 | AP23: Randstad Professional US LP, | AQ23: Billable | AR23: 1 | AW23: Sourcing | AX23: HRCC | AY23: HRCC | AZ23: 90208 | BC23: Considered | CB23: Billed | CC23: US_SAP_L | CD23: 60002 | CE23: 30001312 | CF23: =A23 -> W0004072 | CG23: HR | CH23: =SUM(O23,Q23,T23:X23,) -> 64386.897 | CI23: =SUM(AA23,AC23:AE23) -> 0 | CJ23: =SUM(Z23) -> 12402.5 | CK23: =AJ23 -> 29700 | CL23: =SUM(R23:S23) -> 2054.4361 | CM23: =SUM(AI23,AK23) -> 5427.1916 | CO23: =SUM(CH23:CM23,-AL23) -> 0
A24: W0004073 | B24: GCC0358 | C24: Sabitha Kumari | D24: 42828 | F24: L09 | G24: Talent Services Capability Center | H24: Ankur Sud | I24: IN - Hyderabad_HQ | K24: Unique | L24: Active | M24: 0.05 | N24: 28 | O24: 93143.25 | R24: 2118.8301 | S24: 0 | T24: 220.35833 | U24: 75 | W24: 2868.5107 | X24: 4460.3751 | Y24: 102886.32 | Z24: 4154.1667 | AB24: 107040.49 | AH24: 107040.49 | AI24: 5352.0245 | AJ24: 29700 | AK24: 1485 | AL24: 143577.52 | AM24: Randstad Australia | AN24: RGCC Australia | AO24: 2750 | AP24: Randstad Pty Ltd. | AQ24: Billable | AR24: 1 | AW24: Recruiting(KR) | AX24: RGCC Australia | AY24: RP - Business Support Australia | AZ24: 2750 | BC24: Considered | CB24: Billed | CC24: AU_RAN_L | CD24: 60014 | CE24: 30001338 | CF24: =A24 -> W0004073 | CG24: TS | CH24: =SUM(O24,Q24,T24:X24,) -> 100767.49 | CI24: =SUM(AA24,AC24:AE24) -> 0 | CJ24: =SUM(Z24) -> 4154.1667 | CK24: =AJ24 -> 29700 | CL24: =SUM(R24:S24) -> 2118.8301 | CM24: =SUM(AI24,AK24) -> 6837.0245 | CO24: =SUM(CH24:CM24,-AL24) -> 0
A25: W0004074 | B25: GCC0394 | C25: Naresh Reddy | D25: 42908 | F25: L09 | G25: Talent Services Capability Center | H25: Ankur Sud | I25: IN - Hyderabad_HQ | K25: Unique | L25: Active | M25: 0.05 | N25: 28 | O25: 92424 | R25: 2101.5385 | S25: 1214.2222 | T25: 218.56 | U25: 75 | W25: 0 | X25: 4460.3751 | Y25: 100493.7 | Z25: 4154.1667 | AB25: 104647.86 | AH25: 104647.86 | AI25: 5232.3931 | AJ25: 29700 | AK25: 1485 | AL25: 141065.26 | AM25: RUS | AN25: RUS | AO25: 35887 | AP25: Randstad Professional US LP, | AQ25: Billable | AR25: 1 | AW25: Recruiting(KR) | AX25: RD US | AY25: Digital US - TMT- AAMDP | AZ25: 35887 | BC25: Considered | CB25: Billed | CC25: US_SAP_L | CD25: 60002 | CE25: 30001312 | CF25: =A25 -> W0004074 | CG25: TS | CH25: =SUM(O25,Q25,T25:X25,) -> 97177.935 | CI25: =SUM(AA25,AC25:AE25) -> 0 | CJ25: =SUM(Z25) -> 4154.1667 | CK25: =AJ25 -> 29700 | CL25: =SUM(R25:S25) -> 3315.7607 | CM25: =SUM(AI25,AK25) -> 6717.3931 | CO25: =SUM(CH25:CM25,-AL25) -> 0
A26: W0004075 | B26: GCC0396 | C26: Srikakula Anusha | D26: 42919 | F26: L08 | G26: Finance Capability Center | H26: Abhishek Khurana | I26: IN - Hyderabad_HQ | K26: Unique | L26: Active | M26: 0.085 | N26: 28 | O26: 82289.833 | R26: 1857.9287 | S26: 0 | T26: 193.22458 | U26: 75 | W26: 0 | X26: 4460.3751 | Y26: 88876.362 | Z26: 5687.5 | AB26: 94563.862 | AE26: 7641.9688 | AF26: Deepak Sharma | AG26: GCC1133 | AH26: 102205.83 | AI26: 8687.4956 | AJ26: 29700 | AK26: 2524.5 | AL26: 143117.83 | AM26: Canada | AN26: Canada | AO26: 2933 | AP26: Randstad Interim Inc. | AQ26: Billable | AR26: 1 | AW26: VMS Support and Admin | AX26: CANADA | AY26: RGCC Canada | AZ26: 2933 | BC26: Considered | CB26: Billed | CC26: CA_RIC_SAP | CD26: 60005 | CE26: 30001334 | CF26: =A26 -> W0004075 | CG26: Fin | CH26: =SUM(O26,Q26,T26:X26,) -> 87018.433 | CI26: =SUM(AA26,AC26:AE26) -> 7641.9688 | CJ26: =SUM(Z26) -> 5687.5 | CK26: =AJ26 -> 29700 | CL26: =SUM(R26:S26) -> 1857.9287 | CM26: =SUM(AI26,AK26) -> 11211.996 | CO26: =SUM(CH26:CM26,-AL26) -> 0
A27: W0004076 | B27: GCC0408 | C27: Vinay Malka | D27: 42984 | F27: L06 | G27: Talent Services Capability Center | H27: Ankur Sud | I27: IN - Hyderabad_HQ | K27: Unique | L27: Active | M27: 0.05 | N27: 28 | O27: 157585.08 | R27: 3667.9127 | S27: 2119.2384 | T27: 381.46292 | U27: 75 | W27: 8195.7448 | X27: 4460.3751 | Y27: 176484.82 | Z27: 4154.1667 | AB27: 180638.98 | AH27: 180638.98 | AI27: 9031.9492 | AJ27: 29700 | AK27: 1485 | AL27: 220855.93 | AM27: RUS | AN27: RUS | AO27: 35887 | AP27: Randstad Professional US LP, | AQ27: Billable | AR27: 1 | AW27: Leadership | AX27: RD US | AY27: Digital US - TMT- AAMDP | AZ27: 35887 | BC27: Considered | CB27: Billed | CC27: US_SAP_L | CD27: 60002 | CE27: 30001312 | CF27: =A27 -> W0004076 | CG27: TS | CH27: =SUM(O27,Q27,T27:X27,) -> 170697.67 | CI27: =SUM(AA27,AC27:AE27) -> 0 | CJ27: =SUM(Z27) -> 4154.1667 | CK27: =AJ27 -> 29700 | CL27: =SUM(R27:S27) -> 5787.1511 | CM27: =SUM(AI27,AK27) -> 10516.949 | CO27: =SUM(CH27:CM27,-AL27) -> 0
A28: W0004077 | B28: GCC0422 | C28: Abhinand Kumar | D28: 43026 | F28: L07 | G28: Talent Services Capability Center | H28: Ankur Sud | I28: IN - Hyderabad_HQ | K28: Unique | L28: Active | M28: 0.05 | N28: 28 | O28: 105669.75 | R28: 2419.9479 | S28: 0 | T28: 251.67458 | U28: 75 | W28: 10314.345 | X28: 4460.3751 | Y28: 123191.09 | Z28: 4154.1667 | AB28: 127345.26 | AH28: 127345.26 | AI28: 6367.263 | AJ28: 29700 | AK28: 1485 | AL28: 164897.52 | AM28: RUS | AN28: RUS | AO28: 12021: 20% 19449: 20% 89079: 30% 14411: 10% 17036: 10% | AP28: Randstad Professional US LP, | AQ28: Billable | AR28: 1 | AW28: Recruiting(KR) | AX28: RP | AY28: PTS US Biz Services | AZ28: 12021: 20% 19449: 20% 89079: 30% 14411: 10% 17036: 10% | BC28: Considered | CB28: Billed | CC28: US_SAP_L | CD28: 60002 | CE28: 30001312 | CF28: =A28 -> W0004077 | CG28: TS | CH28: =SUM(O28,Q28,T28:X28,) -> 120771.14 | CI28: =SUM(AA28,AC28:AE28) -> 0 | CJ28: =SUM(Z28) -> 4154.1667 | CK28: =AJ28 -> 29700 | CL28: =SUM(R28:S28) -> 2419.9479 | CM28: =SUM(AI28,AK28) -> 7852.263 | CO28: =SUM(CH28:CM28,-AL28) -> 0
A29: W0004078 | B29: GCC0431 | C29: Bhavani Guru Prasad | D29: 43040 | F29: L08 | G29: Business Operations and Service Delivery | H29: Rishi Kumar Gupta | I29: IN - Hyderabad_HQ | K29: Unique | L29: Active | M29: 0.085 | N29: 28 | O29: 109289.67 | R29: 2506.9631 | S29: 1448.4676 | T29: 260.72417 | U29: 75 | W29: 0 | X29: 4460.3751 | Y29: 118041.2 | Z29: 23570.833 | AB29: 141612.03 | AH29: 141612.03 | AI29: 12037.023 | AJ29: 29700 | AK29: 2524.5 | AL29: 185873.55 | AM29: RUS | AN29: RUS | AO29: 90020 | AP29: Randstad Professional US LP, | AQ29: Billable | AR29: 1 | AW29: Legal | AX29: RUS | AY29: RGCC RUS RBE | AZ29: 90020 | BC29: Considered | CB29: Billed | CC29: US_SAP_L | CD29: 60002 | CE29: 30001312 | CF29: =A29 -> W0004078 | CG29: BO & SD | CH29: =SUM(O29,Q29,T29:X29,) -> 114085.77 | CI29: =SUM(AA29,AC29:AE29) -> 0 | CJ29: =SUM(Z29) -> 23570.833 | CK29: =AJ29 -> 29700 | CL29: =SUM(R29:S29) -> 3955.4307 | CM29: =SUM(AI29,AK29) -> 14561.523 | CO29: =SUM(CH29:CM29,-AL29) -> 0
A30: W0004079 | B30: GCC0444 | C30: Srinivas Jogiparthy | D30: 43059 | F30: L09 | G30: Talent Services Capability Center | H30: Ankur Sud | I30: IN - Hyderabad_HQ | K30: Unique | L30: Active | M30: 0.05 | N30: 28 | O30: 66505.75 | R30: 1478.5056 | S30: 234.91811 | T30: 153.76458 | U30: 75 | W30: 5196.1022 | X30: 4460.3751 | Y30: 78104.416 | Z30: 4154.1667 | AB30: 82258.582 | AH30: 82258.582 | AI30: 4112.9291 | AJ30: 29700 | AK30: 1485 | AL30: 117556.51 | AM30: RUS | AN30: RUS | AO30: 34732 | AP30: Randstad Professional US LP, | AQ30: Billable | AR30: 1 | AW30: Recruiting(KR) | AX30: RE | AY30: RGCC OTS US ENG | AZ30: 34732 | BC30: Considered | CB30: Billed | CC30: US_SAP_L | CD30: 60002 | CE30: 30001312 | CF30: =A30 -> W0004079 | CG30: TS | CH30: =SUM(O30,Q30,T30:X30,) -> 76390.992 | CI30: =SUM(AA30,AC30:AE30) -> 0 | CJ30: =SUM(Z30) -> 4154.1667 | CK30: =AJ30 -> 29700 | CL30: =SUM(R30:S30) -> 1713.4237 | CM30: =SUM(AI30,AK30) -> 5597.9291 | CO30: =SUM(CH30:CM30,-AL30) -> 0
A31: W0004080 | B31: GCC0446 | C31: Anirudh Sangulugari | D31: 43066 | F31: L06 | G31: Talent Services Capability Center | H31: Ankur Sud | I31: IN - Hyderabad_HQ | K31: Unique | L31: Active | M31: 0.05 | N31: 28 | O31: 179016.17 | R31: 4183.0809 | S31: 0 | T31: 435.04042 | U31: 75 | W31: 16758.249 | X31: 4460.3751 | Y31: 204927.91 | Z31: 4154.1667 | AB31: 209082.08 | AH31: 209082.08 | AI31: 10454.104 | AJ31: 29700 | AK31: 1485 | AL31: 250721.18 | AM31: Canada | AN31: Canada | AO31: 2933 | AP31: Randstad Interim Inc. | AQ31: Billable | AR31: 1 | AW31: Leadership | AX31: CANADA | AY31: RGCC RD Canada | AZ31: 2933 | BC31: Considered | CB31: Billed | CC31: CA_RIC_SAP | CD31: 60005 | CE31: 30001334 | CF31: =A31 -> W0004080 | CG31: TS | CH31: =SUM(O31,Q31,T31:X31,) -> 200744.83 | CI31: =SUM(AA31,AC31:AE31) -> 0 | CJ31: =SUM(Z31) -> 4154.1667 | CK31: =AJ31 -> 29700 | CL31: =SUM(R31:S31) -> 4183.0809 | CM31: =SUM(AI31,AK31) -> 11939.104 | CO31: =SUM(CH31:CM31,-AL31) -> 0
A32: W0005291 | B32: GCC0471 | C32: Sai Telkar | D32: 43143 | F32: L07 | G32: Talent Services Capability Center | H32: Ankur Sud | I32: IN - Hyderabad_HQ | K32: Unique | L32: Active | M32: 0.05 | N32: 28 | O32: 103024.58 | R32: 2356.3622 | S32: 0 | T32: 245.06167 | U32: 75 | W32: 9439.449 | X32: 4460.3751 | Y32: 119600.83 | Z32: 4154.1667 | AB32: 123755 | AH32: 123755 | AI32: 6187.7499 | AJ32: 29700 | AK32: 1485 | AL32: 161127.75 | AM32: RUS | AN32: RUS | AO32: 35875 | AP32: Randstad Professional US LP, | AQ32: Billable | AR32: 1 | AW32: Leadership | AX32: RD US | AY32: Digital US - BFSI | AZ32: 35875 | BC32: Considered | CB32: Billed | CC32: US_SAP_L | CD32: 60002 | CE32: 30001312 | CF32: =A32 -> W0005291 | CG32: TS | CH32: =SUM(O32,Q32,T32:X32,) -> 117244.47 | CI32: =SUM(AA32,AC32:AE32) -> 0 | CJ32: =SUM(Z32) -> 4154.1667 | CK32: =AJ32 -> 29700 | CL32: =SUM(R32:S32) -> 2356.3622 | CM32: =SUM(AI32,AK32) -> 7672.7499 | CO32: =SUM(CH32:CM32,-AL32) -> 0
A33: W0004081 | B33: GCC0485 | C33: Kabirunnisa Begum | D33: 43164 | F33: L10 | G33: Talent Services Capability Center | H33: Ankur Sud | I33: IN - Hyderabad_HQ | K33: Unique | L33: Active | M33: 0.05 | N33: 28 | O33: 69831.75 | R33: 1558.4575 | S33: 0 | T33: 162.07958 | U33: 75 | W33: 0 | X33: 4460.3751 | Y33: 76087.662 | Z33: 4154.1667 | AB33: 80241.829 | AH33: 80241.829 | AI33: 4012.0914 | AJ33: 29700 | AK33: 1485 | AL33: 115438.92 | AM33: RUS | AN33: RUS | AO33: 35879 | AP33: Randstad Professional US LP, | AQ33: Billable | AR33: 1 | AW33: Recruiting(KR) | AX33: RD US | AY33: Digital US - ConRtl | AZ33: 35879 | BC33: Considered | CB33: Billed | CC33: US_SAP_L | CD33: 60002 | CE33: 30001312 | CF33: =A33 -> W0004081 | CG33: TS | CH33: =SUM(O33,Q33,T33:X33,) -> 74529.205 | CI33: =SUM(AA33,AC33:AE33) -> 0 | CJ33: =SUM(Z33) -> 4154.1667 | CK33: =AJ33 -> 29700 | CL33: =SUM(R33:S33) -> 1558.4575 | CM33: =SUM(AI33,AK33) -> 5497.0914 | CO33: =SUM(CH33:CM33,-AL33) -> 0
A34: W0005293 | B34: GCC0519 | C34: Divya Janmohan (On Leave) | D34: 43258 | F34: L10 | G34: Talent Services Capability Center | H34: Ankur Sud | I34: IN - Hyderabad_HQ | K34: Unique | L34: Active | M34: 0.05 | N34: 28 | O34: 54844.917 | R34: 1318.3894 | S34: 0 | T34: 137.1125 | U34: 75 | W34: 0 | X34: 4460.3751 | Y34: 60835.794 | Z34: 4154.1667 | AB34: 64989.96 | AE34: 4671.4236 | AF34: Praveen Pallerlamudi | AG34: GCC0204 | AH34: 69661.384 | AI34: 3483.0692 | AJ34: 29700 | AK34: 1485 | AL34: 104329.45 | AM34: Randstad Business solutions Ltd | AN34: Randstad Business solutions Ltd | AO34: C1182_OFFSH | AP34: Randstad Solutions Limited | AQ34: Billable | AR34: 1 | AW34: Recruiting(KR) | AX34: Randstad UK | AY34: PTS UK Care RSW | AZ34: C1182_OFFSH | BC34: Considered | CB34: Billed | CC34: UK_REB_L | CD34: 60009 | CE34: 30001339 | CF34: =A34 -> W0005293 | CG34: TS | CH34: =SUM(O34,Q34,T34:X34,) -> 59517.404 | CI34: =SUM(AA34,AC34:AE34) -> 4671.4236 | CJ34: =SUM(Z34) -> 4154.1667 | CK34: =AJ34 -> 29700 | CL34: =SUM(R34:S34) -> 1318.3894 | CM34: =SUM(AI34,AK34) -> 4968.0692 | CO34: =SUM(CH34:CM34,-AL34) -> 0
A35: W0005294 | B35: GCC0523 | C35: Snigdha Thakker | D35: 43262 | F35: L08 | G35: Finance Capability Center | H35: Abhishek Khurana | I35: IN - Hyderabad_HQ | K35: Unique | L35: Active | M35: 0.085 | N35: 28 | O35: 97732.167 | R35: 2229.1386 | S35: 0 | T35: 231.83042 | U35: 75 | W35: 0 | X35: 4460.3751 | Y35: 104728.51 | Z35: 5687.5 | AB35: 110416.01 | AE35: 6263.256 | AF35: Poojan Gandhi | AG35: GCC1254 | AH35: 116679.27 | AI35: 9917.7377 | AJ35: 29700 | AK35: 2524.5 | AL35: 158821.5 | AM35: RUS | AN35: RUS | AO35: 90349 | AP35: Randstad Professional US LP, | AQ35: Billable | AR35: 1 | AW35: Audit & Assurance | AX35: RUS | AY35: RGCC RUS RBE | AZ35: 90349 | BC35: Considered | CB35: Billed | CC35: US_SAP_L | CD35: 60002 | CE35: 30001312 | CF35: =A35 -> W0005294 | CG35: Fin | CH35: =SUM(O35,Q35,T35:X35,) -> 102499.37 | CI35: =SUM(AA35,AC35:AE35) -> 6263.256 | CJ35: =SUM(Z35) -> 5687.5 | CK35: =AJ35 -> 29700 | CL35: =SUM(R35:S35) -> 2229.1386 | CM35: =SUM(AI35,AK35) -> 12442.238 | CO35: =SUM(CH35:CM35,-AL35) -> 0
A36: W0005124 | B36: GCC0552 | C36: Fatima Khatoon | D36: 43305 | F36: L06 | G36: Talent Services Capability Center | H36: Ankur Sud | I36: IN - Hyderabad_HQ | K36: Unique | L36: Active | M36: 0.05 | N36: 28 | O36: 93910.75 | R36: 2137.2796 | S36: 0 | T36: 222.27708 | U36: 75 | W36: 0 | X36: 4460.3751 | Y36: 100805.68 | Z36: 4154.1667 | AB36: 104959.85 | AH36: 104959.85 | AI36: 5247.9924 | AJ36: 29700 | AK36: 1485 | AL36: 141392.84 | AM36: RGCC Australia | AN36: RGCC Australia | AO36: 5220 | AP36: Randstad Pty Ltd. | AQ36: Billable | AR36: 1 | AW36: Leadership | AX36: RGCC Australia | AY36: RGCC PTS AUS Education | AZ36: 5220 | BC36: Considered | CB36: Billed | CC36: AU_RAN_L | CD36: 60014 | CE36: 30001338 | CF36: =A36 -> W0005124 | CG36: TS | CH36: =SUM(O36,Q36,T36:X36,) -> 98668.402 | CI36: =SUM(AA36,AC36:AE36) -> 0 | CJ36: =SUM(Z36) -> 4154.1667 | CK36: =AJ36 -> 29700 | CL36: =SUM(R36:S36) -> 2137.2796 | CM36: =SUM(AI36,AK36) -> 6732.9924 | CO36: =SUM(CH36:CM36,-AL36) -> 0
A37: W0004083 | B37: GCC0598 | C37: Jagadish Elipilla | D37: 43325 | F37: L08 | G37: Finance Capability Center | H37: Abhishek Khurana | I37: IN - Hyderabad_HQ | K37: Unique | L37: Active | M37: 0.085 | N37: 28 | O37: 103358.08 | R37: 2364.379 | S37: 1366.0856 | T37: 245.89542 | U37: 75 | W37: 0 | X37: 4460.3751 | Y37: 111869.82 | Z37: 5687.5 | AB37: 117557.32 | AE37: 7641.9688 | AF37: Deepak Sharma | AG37: GCC1133 | AH37: 125199.29 | AI37: 10641.939 | AJ37: 29700 | AK37: 2524.5 | AL37: 168065.73 | AM37: RUS | AN37: RUS | AO37: 35072 | AP37: Randstad Professional US LP, | AQ37: Billable | AR37: 1 | AW37: VMS Support and Admin | AX37: RT | AY37: RGCC Other Functional Teams | AZ37: 35072 | BC37: Considered | CB37: Billed | CC37: US_SAP_L | CD37: 60002 | CE37: 30001312 | CF37: =A37 -> W0004083 | CG37: Fin | CH37: =SUM(O37,Q37,T37:X37,) -> 108139.35 | CI37: =SUM(AA37,AC37:AE37) -> 7641.9688 | CJ37: =SUM(Z37) -> 5687.5 | CK37: =AJ37 -> 29700 | CL37: =SUM(R37:S37) -> 3730.4647 | CM37: =SUM(AI37,AK37) -> 13166.439 | CO37: =SUM(CH37:CM37,-AL37) -> 0
A38: W0004084 | B38: GCC0619 | C38: Dhwani Modi | D38: 43353 | F38: L10 | G38: HR Capability Center | H38: Shail Dasika | I38: IN - Hyderabad_HQ | K38: Unique | L38: Active | M38: 0.05 | N38: 28 | O38: 61121.667 | R38: 1469.2708 | S38: 0 | T38: 152.80417 | U38: 75 | W38: 0 | X38: 4460.3751 | Y38: 67279.117 | Z38: 12402.5 | AB38: 79681.617 | AH38: 79681.617 | AI38: 3984.0808 | AJ38: 29700 | AK38: 1485 | AL38: 114850.7 | AM38: Randstad Australia | AN38: RGCC Australia | AO38: 6007 | AP38: Randstad Pty Ltd. | AQ38: Billable | AR38: 1 | AW38: Sourcing | AX38: HRCC | AY38: HRCC | AZ38: 6007 | BC38: Considered | CB38: Billed | CC38: AU_RAN_L | CD38: 60014 | CE38: 30001338 | CF38: =A38 -> W0004084 | CG38: HR | CH38: =SUM(O38,Q38,T38:X38,) -> 65809.846 | CI38: =SUM(AA38,AC38:AE38) -> 0 | CJ38: =SUM(Z38) -> 12402.5 | CK38: =AJ38 -> 29700 | CL38: =SUM(R38:S38) -> 1469.2708 | CM38: =SUM(AI38,AK38) -> 5469.0808 | CO38: =SUM(CH38:CM38,-AL38) -> 0
A39: W0004929 | B39: GCC0644 | C39: Steve Decosta | D39: 43381 | F39: L09 | G39: HR Capability Center | H39: Shail Dasika | I39: IN - Hyderabad_HQ | K39: Unique | L39: Active | M39: 0.05 | N39: 28 | O39: 87830 | R39: 1991.1058 | S39: 1150.4167 | T39: 207.075 | U39: 75 | W39: 0 | X39: 4460.3751 | Y39: 95713.973 | Z39: 12402.5 | AB39: 108116.47 | AH39: 108116.47 | AI39: 5405.8236 | AJ39: 29700 | AK39: 1485 | AL39: 144707.3 | AM39: RUS | AN39: RUS | AO39: 90342 | AP39: Randstad Professional US LP, | AQ39: Billable | AR39: 1 | AW39: Call Center | AX39: HRCC | AY39: HRCC | AZ39: 90342 | BC39: Considered | CB39: Billed | CC39: US_SAP_L | CD39: 60002 | CE39: 30001312 | CF39: =A39 -> W0004929 | CG39: HR | CH39: =SUM(O39,Q39,T39:X39,) -> 92572.45 | CI39: =SUM(AA39,AC39:AE39) -> 0 | CJ39: =SUM(Z39) -> 12402.5 | CK39: =AJ39 -> 29700 | CL39: =SUM(R39:S39) -> 3141.5224 | CM39: =SUM(AI39,AK39) -> 6890.8236 | CO39: =SUM(CH39:CM39,-AL39) -> 0
A40: W0004930 | B40: GCC0654 | C40: Pradeep Pereji | D40: 43395 | F40: L11 | G40: Talent Services Capability Center | H40: Ankur Sud | I40: IN - Hyderabad_HQ | K40: Unique | L40: Active | M40: 0.05 | N40: 28 | O40: 59188.5 | R40: 1302.6082 | S40: 0 | T40: 135.47125 | U40: 75 | W40: 0 | X40: 4460.3751 | Y40: 65161.955 | Z40: 4154.1667 | AB40: 69316.121 | AH40: 69316.121 | AI40: 3465.8061 | AJ40: 29700 | AK40: 1485 | AL40: 103966.93 | AM40: RUS | AN40: RUS | AO40: 35070 | AP40: Randstad Professional US LP, | AQ40: Billable | AR40: 1 | AW40: Operations | AX40: RD US | AY40: Digital US - RITS - TPV | AZ40: 35070 | BC40: Considered | CB40: Billed | CC40: US_SAP_L | CD40: 60002 | CE40: 30001312 | CF40: =A40 -> W0004930 | CG40: TS | CH40: =SUM(O40,Q40,T40:X40,) -> 63859.346 | CI40: =SUM(AA40,AC40:AE40) -> 0 | CJ40: =SUM(Z40) -> 4154.1667 | CK40: =AJ40 -> 29700 | CL40: =SUM(R40:S40) -> 1302.6082 | CM40: =SUM(AI40,AK40) -> 4950.8061 | CO40: =SUM(CH40:CM40,-AL40) -> 0
A41: W0004085 | B41: GCC0668 | C41: Dharani D | D41: 43437 | F41: L06 | G41: Finance Capability Center | H41: Abhishek Khurana | I41: IN - Hyderabad_HQ | K41: Unique | L41: Active | M41: 0.085 | N41: 28 | O41: 135116.67 | R41: 3127.8045 | S41: 0 | T41: 325.29167 | U41: 75 | W41: 0 | X41: 4460.3751 | Y41: 143105.14 | Z41: 5687.5 | AB41: 148792.64 | AE41: 6263.256 | AF41: Poojan Gandhi | AG41: GCC1254 | AH41: 155055.89 | AI41: 13179.751 | AJ41: 29700 | AK41: 2524.5 | AL41: 200460.14 | AM41: RUS | AN41: RUS | AO41: 90349 | AP41: Randstad Professional US LP, | AQ41: Billable | AR41: 1 | AW41: Audit & Assurance | AX41: RUS | AY41: RGCC RUS RBE | AZ41: 90349 | BC41: Considered | CB41: Billed | CC41: US_SAP_L | CD41: 60002 | CE41: 30001312 | CF41: =A41 -> W0004085 | CG41: Fin | CH41: =SUM(O41,Q41,T41:X41,) -> 139977.33 | CI41: =SUM(AA41,AC41:AE41) -> 6263.256 | CJ41: =SUM(Z41) -> 5687.5 | CK41: =AJ41 -> 29700 | CL41: =SUM(R41:S41) -> 3127.8045 | CM41: =SUM(AI41,AK41) -> 15704.251 | CO41: =SUM(CH41:CM41,-AL41) -> 0
A42: W0004086 | B42: GCC0670 | C42: Mohammad Ahmed | D42: 43437 | F42: L09 | G42: Talent Services Capability Center | H42: Ankur Sud | I42: IN - Hyderabad_HQ | K42: Unique | L42: Active | M42: 0.05 | N42: 28 | O42: 99082.75 | R42: 2261.6066 | S42: 0 | T42: 235.20708 | U42: 75 | W42: 0 | X42: 4460.3751 | Y42: 106114.94 | Z42: 4154.1667 | AB42: 110269.11 | AH42: 110269.11 | AI42: 5513.4553 | AJ42: 29700 | AK42: 1485 | AL42: 146967.56 | AM42: RUS | AN42: RUS | AO42: 35880 | AP42: Randstad Professional US LP, | AQ42: Billable | AR42: 1 | AW42: Recruiting(KR) | AX42: RD US | AY42: Digital US -HLS | AZ42: 35880 | BC42: Considered | CB42: Billed | CC42: US_SAP_L | CD42: 60002 | CE42: 30001312 | CF42: =A42 -> W0004086 | CG42: TS | CH42: =SUM(O42,Q42,T42:X42,) -> 103853.33 | CI42: =SUM(AA42,AC42:AE42) -> 0 | CJ42: =SUM(Z42) -> 4154.1667 | CK42: =AJ42 -> 29700 | CL42: =SUM(R42:S42) -> 2261.6066 | CM42: =SUM(AI42,AK42) -> 6998.4553 | CO42: =SUM(CH42:CM42,-AL42) -> 0
A43: W0004087 | B43: GCC0673 | C43: Sravani Salapu | D43: 43439 | F43: L06 | G43: Talent Services Capability Center | H43: Ankur Sud | I43: IN - Hyderabad_HQ | K43: Unique | L43: Active | M43: 0.05 | N43: 28 | O43: 163375.17 | R43: 3807.0954 | S43: 0 | T43: 395.93792 | U43: 75 | W43: 13119.338 | X43: 4460.3751 | Y43: 185232.91 | Z43: 4154.1667 | AB43: 189387.08 | AH43: 189387.08 | AI43: 9469.354 | AJ43: 29700 | AK43: 1485 | AL43: 230041.43 | AM43: Randstad Business solutions Ltd | AN43: Randstad Business solutions Ltd -Digital | AO43: B5500_OFFSH | AP43: Randstad Solutions Limited | AQ43: Billable | AR43: 1 | AW43: Leadership | AX43: Randstad UK | AY43: RGCC RD UK | AZ43: B5500_OFFSH | BC43: Considered | CB43: Billed | CC43: UK_REB_L | CD43: 60009 | CE43: 30001337 | CF43: =A43 -> W0004087 | CG43: TS | CH43: =SUM(O43,Q43,T43:X43,) -> 181425.82 | CI43: =SUM(AA43,AC43:AE43) -> 0 | CJ43: =SUM(Z43) -> 4154.1667 | CK43: =AJ43 -> 29700 | CL43: =SUM(R43:S43) -> 3807.0954 | CM43: =SUM(AI43,AK43) -> 10954.354 | CO43: =SUM(CH43:CM43,-AL43) -> 0
A44: W0004931 | B44: GCC0681 | C44: Nandakishore G S | D44: 43451 | F44: L11 | G44: Talent Services Capability Center | H44: Ankur Sud | I44: IN - Hyderabad_HQ | K44: Unique | L44: Active | M44: 0.05 | N44: 28 | O44: 63192.917 | R44: 1398.8702 | S44: 20.205903 | T44: 145.4825 | U44: 75 | W44: 0 | X44: 4460.3751 | Y44: 69292.85 | Z44: 4154.1667 | AB44: 73447.017 | AH44: 73447.017 | AI44: 3672.3509 | AJ44: 29700 | AK44: 1485 | AL44: 108304.37 | AM44: RUS | AN44: RUS | AO44: 35887 | AP44: Randstad Professional US LP, | AQ44: Billable | AR44: 1 | AW44: Recruiting(KR) | AX44: RD US | AY44: Digital US - TMT- AAMDP | AZ44: 35887 | BC44: Considered | CB44: Billed | CC44: US_SAP_L | CD44: 60002 | CE44: 30001312 | CF44: =A44 -> W0004931 | CG44: TS | CH44: =SUM(O44,Q44,T44:X44,) -> 67873.774 | CI44: =SUM(AA44,AC44:AE44) -> 0 | CJ44: =SUM(Z44) -> 4154.1667 | CK44: =AJ44 -> 29700 | CL44: =SUM(R44:S44) -> 1419.0761 | CM44: =SUM(AI44,AK44) -> 5157.3509 | CO44: =SUM(CH44:CM44,-AL44) -> 0
A45: W0004088 | B45: GCC0699 | C45: Logishetty Kumar | D45: 43479 | F45: L09 | G45: Finance Capability Center | H45: Abhishek Khurana | I45: IN - Hyderabad_HQ | K45: Unique | L45: Active | M45: 0.085 | N45: 28 | O45: 71119.417 | R45: 1589.4111 | S45: 0 | T45: 165.29875 | U45: 75 | W45: 0 | X45: 4460.3751 | Y45: 77409.502 | Z45: 5687.5 | AB45: 83097.002 | AE45: 7641.9688 | AF45: Deepak Sharma | AG45: GCC1133 | AH45: 90738.97 | AI45: 7712.8125 | AJ45: 29700 | AK45: 2524.5 | AL45: 130676.28 | AM45: RUS | AN45: RUS | AO45: 80096 | AP45: Randstad Professional US LP, | AQ45: Billable | AR45: 1 | AW45: Sales Lead Gen/curation | AX45: RUS | AY45: RGCC Other Functional Teams | AZ45: 80096 | BC45: Considered | CB45: Billed | CC45: US_SAP_L | CD45: 60002 | CE45: 30001312 | CF45: =A45 -> W0004088 | CG45: Fin | CH45: =SUM(O45,Q45,T45:X45,) -> 75820.091 | CI45: =SUM(AA45,AC45:AE45) -> 7641.9688 | CJ45: =SUM(Z45) -> 5687.5 | CK45: =AJ45 -> 29700 | CL45: =SUM(R45:S45) -> 1589.4111 | CM45: =SUM(AI45,AK45) -> 10237.312 | CO45: =SUM(CH45:CM45,-AL45) -> 0
A46: W0004089 | B46: GCC0702 | C46: Navneet Singh | D46: 43493 | F46: L06 | G46: Finance Capability Center | H46: Abhishek Khurana | I46: IN - Hyderabad_HQ | K46: Unique | L46: Active | M46: 0.085 | N46: 28 | O46: 126646 | R46: 2924.1827 | S46: 0 | T46: 304.115 | U46: 75 | W46: 6146.8086 | X46: 4460.3751 | Y46: 140556.48 | Z46: 5687.5 | AB46: 146243.98 | AE46: 6107.1874 | AF46: Anurag Kochhar | AG46: GCC0954 | AH46: 152351.17 | AI46: 12949.849 | AJ46: 29700 | AK46: 2524.5 | AL46: 197525.52 | AM46: RUS | AN46: RUS | AO46: 90129 | AP46: Randstad Professional US LP, | AQ46: Billable | AR46: 1 | AW46: Call Center | AX46: GFKS | AY46: RGCC FSSC | AZ46: 90129 | BC46: Considered | CB46: Billed | CC46: US_SAP_L | CD46: 60002 | CE46: 30001312 | CF46: =A46 -> W0004089 | CG46: Fin | CH46: =SUM(O46,Q46,T46:X46,) -> 137632.3 | CI46: =SUM(AA46,AC46:AE46) -> 6107.1874 | CJ46: =SUM(Z46) -> 5687.5 | CK46: =AJ46 -> 29700 | CL46: =SUM(R46:S46) -> 2924.1827 | CM46: =SUM(AI46,AK46) -> 15474.349 | CO46: =SUM(CH46:CM46,-AL46) -> 0
A47: W0004090 | B47: GCC0703 | C47: Harish Pabby | D47: 43493 | F47: L10 | G47: Talent Services Capability Center | H47: Ankur Sud | I47: IN - Hyderabad_HQ | K47: Unique | L47: Active | M47: 0.05 | N47: 28 | O47: 76569.667 | R47: 1720.4247 | S47: 779.31415 | T47: 178.92417 | U47: 75 | W47: 7333.1426 | X47: 4460.3751 | Y47: 91116.847 | Z47: 4154.1667 | AB47: 95271.014 | AH47: 95271.014 | AI47: 4763.5507 | AJ47: 29700 | AK47: 1485 | AL47: 131219.56 | AM47: RUS | AN47: RUS | AO47: 38542 | AP47: Randstad Professional US LP, | AQ47: Billable | AR47: 1 | AW47: Recruiting(KR) | AX47: RLS | AY47: PTS US RLS | AZ47: 38542 | BC47: Considered | CB47: Billed | CC47: US_SAP_L | CD47: 60002 | CE47: 30001312 | CF47: =A47 -> W0004090 | CG47: TS | CH47: =SUM(O47,Q47,T47:X47,) -> 88617.109 | CI47: =SUM(AA47,AC47:AE47) -> 0 | CJ47: =SUM(Z47) -> 4154.1667 | CK47: =AJ47 -> 29700 | CL47: =SUM(R47:S47) -> 2499.7388 | CM47: =SUM(AI47,AK47) -> 6248.5507 | CO47: =SUM(CH47:CM47,-AL47) -> 0
A48: W0004091 | B48: GCC0712 | C48: Acha Ayyappa | D48: 43500 | F48: L06 | G48: Talent Services Capability Center | H48: Ankur Sud | I48: IN - Hyderabad_HQ | K48: Unique | L48: Active | M48: 0.05 | N48: 28 | O48: 150649.25 | R48: 3501.1859 | S48: 0 | T48: 364.12333 | U48: 75 | W48: 0 | X48: 4460.3751 | Y48: 159049.93 | Z48: 4154.1667 | AB48: 163204.1 | AH48: 163204.1 | AI48: 8160.2051 | AJ48: 29700 | AK48: 1485 | AL48: 202549.31 | AM48: RUS | AN48: RUS | AO48: 35879 | AP48: Randstad Professional US LP, | AQ48: Billable | AR48: 1 | AW48: Leadership | AX48: RD US | AY48: Digital US - ConRtl | AZ48: 35879 | BC48: Considered | CB48: Billed | CC48: US_SAP_L | CD48: 60002 | CE48: 30001312 | CF48: =A48 -> W0004091 | CG48: TS | CH48: =SUM(O48,Q48,T48:X48,) -> 155548.75 | CI48: =SUM(AA48,AC48:AE48) -> 0 | CJ48: =SUM(Z48) -> 4154.1667 | CK48: =AJ48 -> 29700 | CL48: =SUM(R48:S48) -> 3501.1859 | CM48: =SUM(AI48,AK48) -> 9645.2051 | CO48: =SUM(CH48:CM48,-AL48) -> 0
A49: W0004092 | B49: GCC0715 | C49: Sai Mani Shankar Chandarllapati | D49: 43507 | F49: L08 | G49: Finance Capability Center | H49: Abhishek Khurana | I49: IN - Hyderabad_HQ | K49: Unique | L49: Active | M49: 0.085 | N49: 28 | O49: 75246.5 | R49: 1688.6178 | S49: 975.64583 | T49: 175.61625 | U49: 75 | W49: 0 | X49: 4460.3751 | Y49: 82621.755 | Z49: 5687.5 | AB49: 88309.255 | AE49: 7641.9688 | AF49: Deepak Sharma | AG49: GCC1133 | AH49: 95951.224 | AI49: 8155.854 | AJ49: 29700 | AK49: 2524.5 | AL49: 136331.58 | AM49: RUS | AN49: RUS | AO49: 34752 | AP49: Randstad Professional US LP, | AQ49: Billable | AR49: 1 | AW49: VMS Support and Admin | AX49: RE | AY49: RE Corporate Accounts | AZ49: 34752 | BC49: Considered | CB49: Billed | CC49: US_SAP_L | CD49: 60002 | CE49: 30001312 | CF49: =A49 -> W0004092 | CG49: Fin | CH49: =SUM(O49,Q49,T49:X49,) -> 79957.491 | CI49: =SUM(AA49,AC49:AE49) -> 7641.9688 | CJ49: =SUM(Z49) -> 5687.5 | CK49: =AJ49 -> 29700 | CL49: =SUM(R49:S49) -> 2664.2636 | CM49: =SUM(AI49,AK49) -> 10680.354 | CO49: =SUM(CH49:CM49,-AL49) -> 0
A50: W0004932 | B50: GCC0729 | C50: Sai Bonela | D50: 43528 | F50: L09 | G50: Talent Services Capability Center | H50: Ankur Sud | I50: IN - Hyderabad_HQ | K50: Unique | L50: Active | M50: 0.05 | N50: 28 | O50: 86101.833 | R50: 1949.5633 | S50: 1126.4144 | T50: 202.75458 | U50: 75 | W50: 8308.4363 | X50: 4460.3751 | Y50: 102224.38 | Z50: 4154.1667 | AB50: 106378.54 | AH50: 106378.54 | AI50: 5318.9272 | AJ50: 29700 | AK50: 1485 | AL50: 142882.47 | AM50: RUS | AN50: RUS | AO50: 19883 | AP50: Randstad Professional US LP, | AQ50: Billable | AR50: 1 | AW50: Recruiting(KR) | AX50: RP | AY50: PTS US VOT | AZ50: 19883 | BC50: Considered | CB50: Billed | CC50: US_SAP_L | CD50: 60002 | CE50: 30001312 | CF50: =A50 -> W0004932 | CG50: TS | CH50: =SUM(O50,Q50,T50:X50,) -> 99148.399 | CI50: =SUM(AA50,AC50:AE50) -> 0 | CJ50: =SUM(Z50) -> 4154.1667 | CK50: =AJ50 -> 29700 | CL50: =SUM(R50:S50) -> 3075.9777 | CM50: =SUM(AI50,AK50) -> 6803.9272 | CO50: =SUM(CH50:CM50,-AL50) -> 0
A51: W0005126 | B51: GCC0732 | C51: Pabbathi Vamsee | D51: 43535 | F51: L09 | G51: Talent Services Capability Center | H51: Ankur Sud | I51: IN - Hyderabad_HQ | K51: Unique | L51: Active | M51: 0.05 | N51: 28 | O51: 75848.5 | R51: 1703.0889 | S51: 704.54897 | T51: 177.12125 | U51: 75 | W51: 7257.332 | X51: 4460.3751 | Y51: 90225.966 | Z51: 4154.1667 | AB51: 94380.133 | AH51: 94380.133 | AI51: 4719.0066 | AJ51: 29700 | AK51: 1485 | AL51: 130284.14 | AM51: RUS | AN51: RUS | AO51: 38542 | AP51: Randstad Professional US LP, | AQ51: Billable | AR51: 1 | AW51: Recruiting(KR) | AX51: RLS | AY51: PTS US RLS | AZ51: 38542 | BC51: Considered | CB51: Billed | CC51: US_SAP_L | CD51: 60002 | CE51: 30001312 | CF51: =A51 -> W0005126 | CG51: TS | CH51: =SUM(O51,Q51,T51:X51,) -> 87818.328 | CI51: =SUM(AA51,AC51:AE51) -> 0 | CJ51: =SUM(Z51) -> 4154.1667 | CK51: =AJ51 -> 29700 | CL51: =SUM(R51:S51) -> 2407.6379 | CM51: =SUM(AI51,AK51) -> 6204.0066 | CO51: =SUM(CH51:CM51,-AL51) -> 0
A52: W0004093 | B52: GCC0736 | C52: Soheil Sharief | D52: 43535 | F52: L06 | G52: Talent Services Capability Center | H52: Ankur Sud | I52: IN - Hyderabad_HQ | K52: Unique | L52: Active | M52: 0.05 | N52: 28 | O52: 134453.75 | R52: 3111.871 | S52: 0 | T52: 323.63458 | U52: 75 | W52: 6146.8086 | X52: 4460.3751 | Y52: 148571.44 | Z52: 4154.1667 | AB52: 152725.61 | AH52: 152725.61 | AI52: 7636.2803 | AJ52: 29700 | AK52: 1485 | AL52: 191546.89 | AM52: RUS | AN52: RUS | AO52: 35880 | AP52: Randstad Professional US LP, | AQ52: Billable | AR52: 1 | AW52: Leadership | AX52: RD US | AY52: Digital US -HLS | AZ52: 35880 | BC52: Considered | CB52: Billed | CC52: US_SAP_L | CD52: 60002 | CE52: 30001312 | CF52: =A52 -> W0004093 | CG52: TS | CH52: =SUM(O52,Q52,T52:X52,) -> 145459.57 | CI52: =SUM(AA52,AC52:AE52) -> 0 | CJ52: =SUM(Z52) -> 4154.1667 | CK52: =AJ52 -> 29700 | CL52: =SUM(R52:S52) -> 3111.871 | CM52: =SUM(AI52,AK52) -> 9121.2803 | CO52: =SUM(CH52:CM52,-AL52) -> 0
A53: W0004094 | B53: GCC0750 | C53: Joseph Irkal | D53: 43570 | F53: L08 | G53: Finance Capability Center | H53: Abhishek Khurana | I53: IN - Hyderabad_HQ | K53: Unique | L53: Active | M53: 0.085 | N53: 28 | O53: 108880.17 | R53: 2497.1194 | S53: 1442.7801 | T53: 259.70042 | U53: 75 | W53: 0 | X53: 4460.3751 | Y53: 117615.14 | Z53: 5687.5 | AB53: 123302.64 | AE53: 4292.2456 | AF53: Vaibhav Patel | AG53: GCC4027 | AH53: 127594.89 | AI53: 10845.565 | AJ53: 29700 | AK53: 2524.5 | AL53: 170664.95 | AM53: RUS | AN53: RUS | AO53: 90294 | AP53: Randstad Professional US LP, | AQ53: Billable | AR53: 1 | AW53: PO Management | AX53: GFKS | AY53: RGCC FSSC | AZ53: 90294 | BC53: Considered | CB53: Billed | CC53: US_SAP_L | CD53: 60002 | CE53: 30001312 | CF53: =A53 -> W0004094 | CG53: Fin | CH53: =SUM(O53,Q53,T53:X53,) -> 113675.24 | CI53: =SUM(AA53,AC53:AE53) -> 4292.2456 | CJ53: =SUM(Z53) -> 5687.5 | CK53: =AJ53 -> 29700 | CL53: =SUM(R53:S53) -> 3939.8995 | CM53: =SUM(AI53,AK53) -> 13370.065 | CO53: =SUM(CH53:CM53,-AL53) -> 0
A54: W0005127 | B54: GCC0763 | C54: Abhishek Khurana | D54: 43591 | F54: L01 | G54: Finance Capability Center | H54: Aqueel Merchant | I54: IN - Hyderabad_HQ | K54: Leaders | L54: Active | M54: 0.085 | N54: 28 | O54: 1571623.8 | P54: 0.22 | Q54: 345757.24 | R54: 37779.419 | S54: 0 | T54: 3929.0596 | U54: 75 | W54: 151346.72 | X54: 5460.3751 | Y54: 2115971.7 | Z54: 5687.5 | AB54: 2121659.2 | AF54: Aqueel Merchant | AG54: GCC4853 | AH54: 2121659.2 | AI54: 180341.03 | AJ54: 29700 | AK54: 2524.5 | AL54: 2334224.7 | AM54: RUS | AN54: Leadership Cost | AO54: 90217 | AP54: RGCC Hyd | AQ54: Non Billable -Leaders | AR54: 1 | AW54: Leadership | AX54: GFKS | AY54: RGCC FSSC | AZ54: 90217 | BC54: Considered | CB54: Unbillled
A55: W0004095 | B55: GCC0764 | C55: Mohammed Mohammed | D55: 43584 | F55: L09 | G55: Enablers-GCC | H55: Sudhir Mohan | I55: IN - Hyderabad_HQ | K55: Unique | L55: Active | M55: 0 | N55: 28 | O55: 77322 | R55: 1738.5096 | S55: 0 | T55: 180.805 | U55: 75 | W55: 0 | X55: 5460.3751 | Y55: 84776.69 | Z55: 0 | AB55: 84776.69 | AH55: 84776.69 | AI55: 0 | AJ55: 29700 | AK55: 0 | AL55: 114476.69 | AM55: RGCC HQ | AN55: RGCC Hyd | AO55: RGCC-HQ | AP55: RGCC Hyd | AQ55: Non Billable | AR55: 1 | AW55: Operations | AX55: RGCC HQ | AY55: RGCC HQ | AZ55: RGCC-HQ | BC55: Considered | CB55: Unbillled
A56: W0004096 | B56: GCC0766 | C56: Santosh Amuda | D56: 43591 | F56: L10 | G56: Talent Services Capability Center | H56: Ankur Sud | I56: IN - Hyderabad_HQ | K56: Unique | L56: Active | M56: 0.05 | N56: 28 | O56: 82099.583 | R56: 1853.3574 | S56: 1070.8287 | T56: 192.74917 | U56: 75 | W56: 0 | X56: 4460.3751 | Y56: 89751.894 | Z56: 4154.1667 | AB56: 93906.06 | AH56: 93906.06 | AI56: 4695.303 | AJ56: 29700 | AK56: 1485 | AL56: 129786.36 | AM56: RUS | AN56: RUS | AO56: 35070 | AP56: Randstad Professional US LP, | AQ56: Billable | AR56: 1 | AW56: Recruiting(KR) | AX56: RD US | AY56: Digital US - RITS - TPV | AZ56: 35070 | BC56: Considered | CB56: Billed | CC56: US_SAP_L | CD56: 60002 | CE56: 30001312 | CF56: =A56 -> W0004096 | CG56: TS | CH56: =SUM(O56,Q56,T56:X56,) -> 86827.708 | CI56: =SUM(AA56,AC56:AE56) -> 0 | CJ56: =SUM(Z56) -> 4154.1667 | CK56: =AJ56 -> 29700 | CL56: =SUM(R56:S56) -> 2924.1861 | CM56: =SUM(AI56,AK56) -> 6180.303 | CO56: =SUM(CH56:CM56,-AL56) -> 0
A57: W0004097 | B57: GCC0779 | C57: Ghouse Mohammed | D57: 43598 | F57: L10 | G57: Talent Services Capability Center | H57: Ankur Sud | I57: IN - Hyderabad_HQ | K57: Unique | L57: Active | M57: 0.05 | N57: 28 | O57: 63105.5 | R57: 1396.7668 | S57: 0 | T57: 145.26375 | U57: 75 | W57: 0 | X57: 4460.3751 | Y57: 69182.906 | Z57: 4154.1667 | AB57: 73337.072 | AH57: 73337.072 | AI57: 3666.8536 | AJ57: 29700 | AK57: 1485 | AL57: 108188.93 | AM57: RUS | AN57: RUS | AO57: 35880 | AP57: Randstad Professional US LP, | AQ57: Billable | AR57: 1 | AW57: Recruiting(KR) | AX57: RD US | AY57: Digital US -HLS | AZ57: 35880 | BC57: Considered | CB57: Billed | CC57: US_SAP_L | CD57: 60002 | CE57: 30001312 | CF57: =A57 -> W0004097 | CG57: TS | CH57: =SUM(O57,Q57,T57:X57,) -> 67786.139 | CI57: =SUM(AA57,AC57:AE57) -> 0 | CJ57: =SUM(Z57) -> 4154.1667 | CK57: =AJ57 -> 29700 | CL57: =SUM(R57:S57) -> 1396.7668 | CM57: =SUM(AI57,AK57) -> 5151.8536 | CO57: =SUM(CH57:CM57,-AL57) -> 0
A58: W0004933 | B58: GCC0783 | C58: Sai Konda | D58: 43599 | F58: L08 | G58: Finance Capability Center | H58: Abhishek Khurana | I58: IN - Hyderabad_HQ | K58: Unique | L58: Active | M58: 0.085 | N58: 28 | O58: 103163.25 | R58: 2359.6955 | S58: 0 | T58: 245.40833 | U58: 75 | W58: 0 | X58: 4460.3751 | Y58: 110303.73 | Z58: 5687.5 | AB58: 115991.23 | AE58: 4292.2456 | AF58: Vaibhav Patel | AG58: GCC4027 | AH58: 120283.47 | AI58: 10224.095 | AJ58: 29700 | AK58: 2524.5 | AL58: 162732.07 | AM58: RUS | AN58: RUS | AO58: 90242 | AP58: Randstad Professional US LP, | AQ58: Billable | AR58: 1 | AW58: Cash Application | AX58: GFKS | AY58: RGCC FSSC | AZ58: 90242 | BC58: Considered | CB58: Billed | CC58: US_SAP_L | CD58: 60002 | CE58: 30001312 | CF58: =A58 -> W0004933 | CG58: Fin | CH58: =SUM(O58,Q58,T58:X58,) -> 107944.03 | CI58: =SUM(AA58,AC58:AE58) -> 4292.2456 | CJ58: =SUM(Z58) -> 5687.5 | CK58: =AJ58 -> 29700 | CL58: =SUM(R58:S58) -> 2359.6955 | CM58: =SUM(AI58,AK58) -> 12748.595 | CO58: =SUM(CH58:CM58,-AL58) -> 0
A59: W0005295 | B59: GCC0788 | C59: Sai Karne | D59: 43598 | F59: L08 | G59: Finance Capability Center | H59: Abhishek Khurana | I59: IN - Hyderabad_HQ | K59: Unique | L59: Active | M59: 0.085 | N59: 28 | O59: 101137.75 | R59: 2311.0056 | S59: 0 | T59: 240.34458 | U59: 75 | W59: 0 | X59: 4460.3751 | Y59: 108224.48 | Z59: 5687.5 | AB59: 113911.98 | AE59: 6263.256 | AF59: Poojan Gandhi | AG59: GCC1254 | AH59: 120175.23 | AI59: 10214.895 | AJ59: 29700 | AK59: 2524.5 | AL59: 162614.63 | AM59: RUS | AN59: RUS | AO59: 14684 | AP59: Randstad Professional US LP, | AQ59: Billable | AR59: 1 | AW59: Field Operations | AX59: GFKS | AY59: RGCC RTG Enablement | AZ59: 14684 | BC59: Considered | CB59: Billed | CC59: US_SAP_L | CD59: 60002 | CE59: 30001312 | CF59: =A59 -> W0005295 | CG59: Fin | CH59: =SUM(O59,Q59,T59:X59,) -> 105913.47 | CI59: =SUM(AA59,AC59:AE59) -> 6263.256 | CJ59: =SUM(Z59) -> 5687.5 | CK59: =AJ59 -> 29700 | CL59: =SUM(R59:S59) -> 2311.0056 | CM59: =SUM(AI59,AK59) -> 12739.395 | CO59: =SUM(CH59:CM59,-AL59) -> 0
A60: W0004098 | B60: GCC0790 | C60: Maheshwari Patel | D60: 43593 | F60: L09 | G60: Finance Capability Center | H60: Abhishek Khurana | I60: IN - Hyderabad_HQ | K60: Unique | L60: Active | M60: 0.085 | N60: 28 | O60: 85224.667 | R60: 1928.4776 | S60: 947.09676 | T60: 200.56167 | U60: 75 | W60: 0 | X60: 4460.3751 | Y60: 92836.178 | Z60: 5687.5 | AB60: 98523.678 | AE60: 4292.2456 | AF60: Vaibhav Patel | AG60: GCC4027 | AH60: 102815.92 | AI60: 8739.3535 | AJ60: 29700 | AK60: 2524.5 | AL60: 143779.78 | AM60: RUS | AN60: RUS | AO60: 90382 | AP60: Randstad Professional US LP, | AQ60: Billable | AR60: 1 | AW60: VMS Reconciliations | AX60: GFKS | AY60: RGCC FSSC | AZ60: 90382 | BC60: Considered | CB60: Billed | CC60: US_SAP_L | CD60: 60002 | CE60: 30001312 | CF60: =A60 -> W0004098 | CG60: Fin | CH60: =SUM(O60,Q60,T60:X60,) -> 89960.603 | CI60: =SUM(AA60,AC60:AE60) -> 4292.2456 | CJ60: =SUM(Z60) -> 5687.5 | CK60: =AJ60 -> 29700 | CL60: =SUM(R60:S60) -> 2875.5743 | CM60: =SUM(AI60,AK60) -> 11263.853 | CO60: =SUM(CH60:CM60,-AL60) -> 0
A61: W0004934 | B61: GCC0791 | C61: Prashanth Nizamabad | D61: 43598 | F61: L10 | G61: Talent Services Capability Center | H61: Ankur Sud | I61: IN - Hyderabad_HQ | K61: Unique | L61: Active | M61: 0.05 | N61: 28 | O61: 78075.167 | R61: 1756.6146 | S61: 0 | T61: 182.68792 | U61: 75 | W61: 0 | X61: 4460.3751 | Y61: 84549.844 | Z61: 4154.1667 | AB61: 88704.011 | AH61: 88704.011 | AI61: 4435.2005 | AJ61: 29700 | AK61: 1485 | AL61: 124324.21 | AM61: RUS | AN61: RUS | AO61: 35879 | AP61: Randstad Professional US LP, | AQ61: Billable | AR61: 1 | AW61: Recruiting(KR) | AX61: RD US | AY61: Digital US - ConRtl | AZ61: 35879 | BC61: Considered | CB61: Billed | CC61: US_SAP_L | CD61: 60002 | CE61: 30001312 | CF61: =A61 -> W0004934 | CG61: TS | CH61: =SUM(O61,Q61,T61:X61,) -> 82793.23 | CI61: =SUM(AA61,AC61:AE61) -> 0 | CJ61: =SUM(Z61) -> 4154.1667 | CK61: =AJ61 -> 29700 | CL61: =SUM(R61:S61) -> 1756.6146 | CM61: =SUM(AI61,AK61) -> 5920.2005 | CO61: =SUM(CH61:CM61,-AL61) -> 0
A62: W0004099 | B62: GCC0823 | C62: Srikanth Udatha | D62: 43633 | F62: L08 | G62: Finance Capability Center | H62: Abhishek Khurana | I62: IN - Hyderabad_HQ | K62: Unique | L62: Active | M62: 0.085 | N62: 28 | O62: 136683.75 | R62: 3165.4768 | S62: 1828.9421 | T62: 329.20958 | U62: 75 | W62: 2048.9362 | X62: 4460.3751 | Y62: 148591.69 | Z62: 5687.5 | AB62: 154279.19 | AE62: 6263.256 | AF62: Poojan Gandhi | AG62: GCC1254 | AH62: 160542.45 | AI62: 13646.108 | AJ62: 29700 | AK62: 2524.5 | AL62: 206413.05 | AM62: RUS | AN62: RUS | AO62: 90349 | AP62: Randstad Professional US LP, | AQ62: Billable | AR62: 1 | AW62: Service Delivery | AX62: GFKS | AY62: RGCC FSSC | AZ62: 90349 | BC62: Considered | CB62: Billed | CC62: US_SAP_L | CD62: 60002 | CE62: 30001312 | CF62: =A62 -> W0004099 | CG62: Fin | CH62: =SUM(O62,Q62,T62:X62,) -> 143597.27 | CI62: =SUM(AA62,AC62:AE62) -> 6263.256 | CJ62: =SUM(Z62) -> 5687.5 | CK62: =AJ62 -> 29700 | CL62: =SUM(R62:S62) -> 4994.4189 | CM62: =SUM(AI62,AK62) -> 16170.608 | CO62: =SUM(CH62:CM62,-AL62) -> 0
A63: W0004100 | B63: GCC0832 | C63: Soundarya Chinnapaga | D63: 43633 | F63: L10 | G63: Talent Services Capability Center | H63: Ankur Sud | I63: IN - Hyderabad_HQ | K63: Unique | L63: Active | M63: 0.05 | N63: 28 | O63: 62057 | R63: 1371.5625 | S63: 792.45833 | T63: 142.6425 | U63: 75 | W63: 0 | X63: 4460.3751 | Y63: 68899.038 | Z63: 4154.1667 | AB63: 73053.205 | AH63: 73053.205 | AI63: 3652.6603 | AJ63: 29700 | AK63: 1485 | AL63: 107890.87 | AM63: RUS | AN63: RUS | AO63: 35070 | AP63: Randstad Professional US LP, | AQ63: Billable | AR63: 1 | AW63: Operations | AX63: RD US | AY63: Digital US - RITS - TPV | AZ63: 35070 | BC63: Considered | CB63: Billed | CC63: US_SAP_L | CD63: 60002 | CE63: 30001312 | CF63: =A63 -> W0004100 | CG63: TS | CH63: =SUM(O63,Q63,T63:X63,) -> 66735.018 | CI63: =SUM(AA63,AC63:AE63) -> 0 | CJ63: =SUM(Z63) -> 4154.1667 | CK63: =AJ63 -> 29700 | CL63: =SUM(R63:S63) -> 2164.0208 | CM63: =SUM(AI63,AK63) -> 5137.6603 | CO63: =SUM(CH63:CM63,-AL63) -> 0
A64: W0004101 | B64: GCC0834 | C64: Phaneeswar Makham | D64: 43654 | F64: L08 | G64: Finance Capability Center | H64: Abhishek Khurana | I64: IN - Hyderabad_HQ | K64: Unique | L64: Active | M64: 0.085 | N64: 28 | O64: 108881.83 | R64: 2497.1595 | S64: 0 | T64: 259.70458 | U64: 75 | W64: 0 | X64: 4460.3751 | Y64: 116174.07 | Z64: 5687.5 | AB64: 121861.57 | AE64: 4292.2456 | AF64: Vaibhav Patel | AG64: GCC4027 | AH64: 126153.82 | AI64: 10723.075 | AJ64: 29700 | AK64: 2524.5 | AL64: 169101.39 | AM64: RUS | AN64: RUS | AO64: 90294 | AP64: Randstad Professional US LP, | AQ64: Billable | AR64: 1 | AW64: COS and centralized setup | AX64: GFKS | AY64: RGCC FSSC | AZ64: 90294 | BC64: Considered | CB64: Billed | CC64: US_SAP_L | CD64: 60002 | CE64: 30001312 | CF64: =A64 -> W0004101 | CG64: Fin | CH64: =SUM(O64,Q64,T64:X64,) -> 113676.91 | CI64: =SUM(AA64,AC64:AE64) -> 4292.2456 | CJ64: =SUM(Z64) -> 5687.5 | CK64: =AJ64 -> 29700 | CL64: =SUM(R64:S64) -> 2497.1595 | CM64: =SUM(AI64,AK64) -> 13247.575 | CO64: =SUM(CH64:CM64,-AL64) -> 0
A65: W0004102 | B65: GCC0837 | C65: Vijay Kumar Amula | D65: 43654 | F65: L11 | G65: Talent Services Capability Center | H65: Ankur Sud | I65: IN - Hyderabad_HQ | K65: Unique | L65: Active | M65: 0.05 | N65: 28 | O65: 59648.417 | R65: 1313.6659 | S65: 759.00694 | T65: 136.62125 | U65: 75 | W65: 0 | X65: 4460.3751 | Y65: 66393.086 | Z65: 4154.1667 | AB65: 70547.253 | AH65: 70547.253 | AI65: 3527.3626 | AJ65: 29700 | AK65: 1485 | AL65: 105259.62 | AM65: RUS | AN65: RUS | AO65: 35070 | AP65: Randstad Professional US LP, | AQ65: Billable | AR65: 1 | AW65: Operations | AX65: RD US | AY65: Digital US - RITS - TPV | AZ65: 35070 | BC65: Considered | CB65: Billed | CC65: US_SAP_L | CD65: 60002 | CE65: 30001312 | CF65: =A65 -> W0004102 | CG65: TS | CH65: =SUM(O65,Q65,T65:X65,) -> 64320.413 | CI65: =SUM(AA65,AC65:AE65) -> 0 | CJ65: =SUM(Z65) -> 4154.1667 | CK65: =AJ65 -> 29700 | CL65: =SUM(R65:S65) -> 2072.6728 | CM65: =SUM(AI65,AK65) -> 5012.3626 | CO65: =SUM(CH65:CM65,-AL65) -> 0
A66: W0004103 | B66: GCC0838 | C66: Varchas Ammanabolu | D66: 43654 | F66: L09 | G66: Finance Capability Center | H66: Abhishek Khurana | I66: IN - Hyderabad_HQ | K66: Unique | L66: Active | M66: 0.085 | N66: 28 | O66: 102365.58 | R66: 2340.5208 | S66: 1352.3009 | T66: 243.41417 | U66: 75 | W66: 8195.7448 | X66: 4460.3751 | Y66: 119032.94 | Z66: 5687.5 | AB66: 124720.44 | AE66: 6263.256 | AF66: Poojan Gandhi | AG66: GCC1254 | AH66: 130983.7 | AI66: 11133.614 | AJ66: 29700 | AK66: 2524.5 | AL66: 174341.81 | AM66: RUS | AN66: RUS | AO66: 94617 | AP66: Randstad Professional US LP, | AQ66: Billable | AR66: 1 | AW66: Service Delivery | AX66: GFKS | AY66: RGCC FSSC | AZ66: 94617 | BC66: Considered | CB66: Billed | CC66: US_SAP_L | CD66: 60002 | CE66: 30001312 | CF66: =A66 -> W0004103 | CG66: Fin | CH66: =SUM(O66,Q66,T66:X66,) -> 115340.12 | CI66: =SUM(AA66,AC66:AE66) -> 6263.256 | CJ66: =SUM(Z66) -> 5687.5 | CK66: =AJ66 -> 29700 | CL66: =SUM(R66:S66) -> 3692.8218 | CM66: =SUM(AI66,AK66) -> 13658.114 | CO66: =SUM(CH66:CM66,-AL66) -> 0
A67: W0004104 | B67: GCC0843 | C67: Jasper Thogaru | D67: 43654 | F67: L09 | G67: Finance Capability Center | H67: Abhishek Khurana | I67: IN - Hyderabad_HQ | K67: Unique | L67: Active | M67: 0.085 | N67: 28 | O67: 110786.58 | R67: 2542.9487 | S67: 0 | T67: 264.46667 | U67: 75 | W67: 9267.3384 | X67: 4460.3751 | Y67: 127396.71 | Z67: 5687.5 | AB67: 133084.21 | AE67: 6263.256 | AF67: Poojan Gandhi | AG67: GCC1254 | AH67: 139347.47 | AI67: 11844.535 | AJ67: 29700 | AK67: 2524.5 | AL67: 183416.5 | AM67: RUS | AN67: RUS | AO67: 90264 | AP67: Randstad Professional US LP, | AQ67: Billable | AR67: 1 | AW67: Service Delivery | AX67: GFKS | AY67: RGCC FSSC | AZ67: 90264 | BC67: Considered | CB67: Billed | CC67: US_SAP_L | CD67: 60002 | CE67: 30001312 | CF67: =A67 -> W0004104 | CG67: Fin | CH67: =SUM(O67,Q67,T67:X67,) -> 124853.76 | CI67: =SUM(AA67,AC67:AE67) -> 6263.256 | CJ67: =SUM(Z67) -> 5687.5 | CK67: =AJ67 -> 29700 | CL67: =SUM(R67:S67) -> 2542.9487 | CM67: =SUM(AI67,AK67) -> 14369.035 | CO67: =SUM(CH67:CM67,-AL67) -> 0
A68: W0005128 | B68: GCC0850 | C68: Dinesh Singh | D68: 43668 | F68: L08 | G68: Finance Capability Center | H68: Abhishek Khurana | I68: IN - Hyderabad_HQ | K68: Unique | L68: Active | M68: 0.085 | N68: 28 | O68: 96405.833 | R68: 2197.2556 | S68: 1269.5255 | T68: 228.51458 | U68: 75 | W68: 0 | X68: 4460.3751 | Y68: 104636.5 | Z68: 5687.5 | AB68: 110324 | AE68: 4292.2456 | AF68: Vaibhav Patel | AG68: GCC4027 | AH68: 114616.25 | AI68: 9742.3812 | AJ68: 29700 | AK68: 2524.5 | AL68: 156583.13 | AM68: RUS | AN68: RUS | AO68: 90242 | AP68: Randstad Professional US LP, | AQ68: Billable | AR68: 1 | AW68: AR | AX68: GFKS | AY68: RGCC FSSC | AZ68: 90242 | BC68: Considered | CB68: Billed | CC68: US_SAP_L | CD68: 60002 | CE68: 30001312 | CF68: =A68 -> W0005128 | CG68: Fin | CH68: =SUM(O68,Q68,T68:X68,) -> 101169.72 | CI68: =SUM(AA68,AC68:AE68) -> 4292.2456 | CJ68: =SUM(Z68) -> 5687.5 | CK68: =AJ68 -> 29700 | CL68: =SUM(R68:S68) -> 3466.7811 | CM68: =SUM(AI68,AK68) -> 12266.881 | CO68: =SUM(CH68:CM68,-AL68) -> 0
A69: W0005129 | B69: GCC0860 | C69: Harish Midgay | D69: 43675 | F69: L10 | G69: Talent Services Capability Center | H69: Ankur Sud | I69: IN - Hyderabad_HQ | K69: Unique | L69: Active | M69: 0.05 | N69: 28 | O69: 90584.083 | R69: 2057.3117 | S69: 1055.5381 | T69: 213.96042 | U69: 75 | W69: 0 | X69: 4460.3751 | Y69: 98446.269 | Z69: 4154.1667 | AB69: 102600.44 | AH69: 102600.44 | AI69: 5130.0218 | AJ69: 29700 | AK69: 1485 | AL69: 138915.46 | AM69: RUS | AN69: RUS | AO69: 35879 | AP69: Randstad Professional US LP, | AQ69: Billable | AR69: 1 | AW69: Recruiting(KR) | AX69: RD US | AY69: Digital US - ConRtl | AZ69: 35879 | BC69: Considered | CB69: Billed | CC69: US_SAP_L | CD69: 60002 | CE69: 30001312 | CF69: =A69 -> W0005129 | CG69: TS | CH69: =SUM(O69,Q69,T69:X69,) -> 95333.419 | CI69: =SUM(AA69,AC69:AE69) -> 0 | CJ69: =SUM(Z69) -> 4154.1667 | CK69: =AJ69 -> 29700 | CL69: =SUM(R69:S69) -> 3112.8498 | CM69: =SUM(AI69,AK69) -> 6615.0218 | CO69: =SUM(CH69:CM69,-AL69) -> 0
A70: W0004105 | B70: GCC0863 | C70: Shailesh Shrivastava | D70: 43682 | F70: L10 | G70: Talent Services Capability Center | H70: Ankur Sud | I70: IN - Hyderabad_HQ | K70: Unique | L70: Active | M70: 0.05 | N70: 28 | O70: 66024.25 | R70: 1587.1234 | S70: 840.89325 | T70: 165.06083 | U70: 75 | W70: 6357.849 | X70: 4460.3751 | Y70: 79510.552 | Z70: 4154.1667 | AB70: 83664.718 | AE70: 4671.4236 | AF70: Praveen Pallerlamudi | AG70: GCC0204 | AH70: 88336.142 | AI70: 4416.8071 | AJ70: 29700 | AK70: 1485 | AL70: 123937.95 | AM70: Randstad Business solutions Ltd | AN70: Randstad Business solutions Ltd | AO70: D9503_OFFSH | AP70: Randstad Solutions Limited | AQ70: Billable | AR70: 1 | AW70: Recruiting(KR) | AX70: Randstad UK | AY70: OTS UK CPE FM Temp | AZ70: D9503_OFFSH | BC70: Considered | CB70: Billed | CC70: UK_REB_L | CD70: 60009 | CE70: 30001339 | CF70: =A70 -> W0004105 | CG70: TS | CH70: =SUM(O70,Q70,T70:X70,) -> 77082.535 | CI70: =SUM(AA70,AC70:AE70) -> 4671.4236 | CJ70: =SUM(Z70) -> 4154.1667 | CK70: =AJ70 -> 29700 | CL70: =SUM(R70:S70) -> 2428.0166 | CM70: =SUM(AI70,AK70) -> 5901.8071 | CO70: =SUM(CH70:CM70,-AL70) -> 0
A71: W0005130 | B71: GCC0870 | C71: Sneha Gontu | D71: 43689 | F71: L10 | G71: Finance Capability Center | H71: Abhishek Khurana | I71: IN - Hyderabad_HQ | K71: Unique | L71: Active | M71: 0.085 | N71: 28 | O71: 70511.25 | R71: 1574.7917 | S71: 909.87963 | T71: 163.77833 | U71: 75 | W71: 0 | X71: 4460.3751 | Y71: 77695.075 | Z71: 5687.5 | AB71: 83382.575 | AE71: 6107.1874 | AF71: Anurag Kochhar | AG71: GCC0954 | AH71: 89489.762 | AI71: 7606.6298 | AJ71: 29700 | AK71: 2524.5 | AL71: 129320.89 | AM71: RUS | AN71: RUS | AO71: 90129 | AP71: Randstad Professional US LP, | AQ71: Billable | AR71: 1 | AW71: Call Center | AX71: GFKS | AY71: RGCC FSSC | AZ71: 90129 | BC71: Considered | CB71: Billed | CC71: US_SAP_L | CD71: 60002 | CE71: 30001312 | CF71: =A71 -> W0005130 | CG71: Fin | CH71: =SUM(O71,Q71,T71:X71,) -> 75210.403 | CI71: =SUM(AA71,AC71:AE71) -> 6107.1874 | CJ71: =SUM(Z71) -> 5687.5 | CK71: =AJ71 -> 29700 | CL71: =SUM(R71:S71) -> 2484.6713 | CM71: =SUM(AI71,AK71) -> 10131.13 | CO71: =SUM(CH71:CM71,-AL71) -> 0
A72: W0004935 | B72: GCC0885 | C72: Merugu Kumar | D72: 43696 | F72: L11 | G72: Talent Services Capability Center | H72: Ankur Sud | I72: IN - Hyderabad_HQ | K72: Unique | L72: Active | M72: 0.05 | N72: 28 | O72: 68547.583 | R72: 1567.9768 | S72: 0 | T72: 163.06958 | U72: 75 | W72: 6109.9277 | X72: 4460.3751 | Y72: 80923.933 | Z72: 4154.1667 | AB72: 85078.099 | AH72: 85078.099 | AI72: 4253.905 | AJ72: 29700 | AK72: 1485 | AL72: 120517 | AM72: Randstad Business solutions Ltd | AN72: Randstad Business solutions Ltd -Digital | AO72: B5500_OFFSH | AP72: Randstad Solutions Limited | AQ72: Billable | AR72: 1 | AW72: Recruiting(KR) | AX72: Randstad UK | AY72: RGCC RUK Digital | AZ72: B5500_OFFSH | BC72: Considered | CB72: Billed | CC72: UK_REB_L | CD72: 60009 | CE72: 30001337 | CF72: =A72 -> W0004935 | CG72: TS | CH72: =SUM(O72,Q72,T72:X72,) -> 79355.956 | CI72: =SUM(AA72,AC72:AE72) -> 0 | CJ72: =SUM(Z72) -> 4154.1667 | CK72: =AJ72 -> 29700 | CL72: =SUM(R72:S72) -> 1567.9768 | CM72: =SUM(AI72,AK72) -> 5738.905 | CO72: =SUM(CH72:CM72,-AL72) -> 0
A73: W0004107 | B73: GCC0908 | C73: Azher Mohammed | D73: 43717 | F73: L09 | G73: Finance Capability Center | H73: Abhishek Khurana | I73: IN - Hyderabad_HQ | K73: Unique | L73: Active | M73: 0.085 | N73: 28 | O73: 54394.5 | R73: 1187.3678 | S73: 91.928653 | T73: 123.48625 | U73: 75 | W73: 0 | X73: 4460.3751 | Y73: 60332.658 | Z73: 5687.5 | AB73: 66020.158 | AE73: 4292.2456 | AF73: Vaibhav Patel | AG73: GCC4027 | AH73: 70312.403 | AI73: 5976.5543 | AJ73: 29700 | AK73: 2524.5 | AL73: 108513.46 | AM73: RUS | AN73: RUS | AO73: 90294 | AP73: Randstad Professional US LP, | AQ73: Billable | AR73: 1 | AW73: COS and centralized setup | AX73: GFKS | AY73: RGCC FSSC | AZ73: 90294 | BC73: Considered | CB73: Billed | CC73: US_SAP_L | CD73: 60002 | CE73: 30001312 | CF73: =A73 -> W0004107 | CG73: Fin | CH73: =SUM(O73,Q73,T73:X73,) -> 59053.361 | CI73: =SUM(AA73,AC73:AE73) -> 4292.2456 | CJ73: =SUM(Z73) -> 5687.5 | CK73: =AJ73 -> 29700 | CL73: =SUM(R73:S73) -> 1279.2964 | CM73: =SUM(AI73,AK73) -> 8501.0543 | CO73: =SUM(CH73:CM73,-AL73) -> 0
A74: W0004108 | B74: GCC0923 | C74: Kaneez Fatima | D74: 43731 | F74: L08 | G74: Finance Capability Center | H74: Abhishek Khurana | I74: IN - Hyderabad_HQ | K74: Unique | L74: Active | M74: 0.085 | N74: 28 | O74: 98125.75 | R74: 2238.6018 | S74: 0 | T74: 232.81458 | U74: 75 | W74: 0 | X74: 4460.3751 | Y74: 105132.54 | Z74: 5687.5 | AB74: 110820.04 | AE74: 18525.414 | AF74: Devraj Ravindernath | AG74: GCC1010 | AH74: 129345.46 | AI74: 10994.364 | AJ74: 29700 | AK74: 2524.5 | AL74: 172564.32 | AM74: RUS | AN74: RUS | AO74: 90353 | AP74: Randstad Professional US LP, | AQ74: Billable | AR74: 1 | AW74: Procurement | AX74: GFKS | AY74: RGCC FSSC | AZ74: 90353 | BC74: Considered | CB74: Billed | CC74: US_SAP_L | CD74: 60002 | CE74: 30001312 | CF74: =A74 -> W0004108 | CG74: Fin | CH74: =SUM(O74,Q74,T74:X74,) -> 102893.94 | CI74: =SUM(AA74,AC74:AE74) -> 18525.414 | CJ74: =SUM(Z74) -> 5687.5 | CK74: =AJ74 -> 29700 | CL74: =SUM(R74:S74) -> 2238.6018 | CM74: =SUM(AI74,AK74) -> 13518.864 | CO74: =SUM(CH74:CM74,-AL74) -> 0
A75: W0005296 | B75: GCC0942 | C75: Abhishek Agarwal | D75: 43752 | F75: L05 | G75: Talent Services Capability Center | H75: Ankur Sud | I75: IN - Hyderabad_HQ | K75: Unique | L75: Active | M75: 0.05 | N75: 28 | O75: 184624.67 | Q75: 0 | R75: 4317.9006 | S75: 2494.787 | T75: 449.06167 | U75: 75 | W75: 10244.681 | X75: 4460.3751 | Y75: 206666.47 | Z75: 4154.1667 | AB75: 210820.64 | AH75: 210820.64 | AI75: 10541.032 | AJ75: 29700 | AK75: 1485 | AL75: 252546.67 | AM75: RUS | AN75: RUS | AO75: 35887 | AP75: Randstad Professional US LP, | AQ75: Billable | AR75: 1 | AW75: Recruiting(KR) | AX75: RD US | AY75: Digital US - TMT- AAMDP | AZ75: 35887 | BC75: Considered | CB75: Billed | CC75: US_SAP_L | CD75: 60002 | CE75: 30001312 | CF75: =A75 -> W0005296 | CG75: TS | CH75: =SUM(O75,Q75,T75:X75,) -> 199853.78 | CI75: =SUM(AA75,AC75:AE75) -> 0 | CJ75: =SUM(Z75) -> 4154.1667 | CK75: =AJ75 -> 29700 | CL75: =SUM(R75:S75) -> 6812.6877 | CM75: =SUM(AI75,AK75) -> 12026.032 | CO75: =SUM(CH75:CM75,-AL75) -> 0
A76: W0004109 | B76: GCC0945 | C76: Susana Goneh | D76: 43759 | F76: L09 | G76: Finance Capability Center | H76: Abhishek Khurana | I76: IN - Hyderabad_HQ | K76: Unique | L76: Active | M76: 0.085 | N76: 28 | O76: 81443.583 | R76: 1837.5881 | S76: 1061.7176 | T76: 191.10917 | U76: 75 | W76: 3915.5171 | X76: 4460.3751 | Y76: 92984.89 | Z76: 5687.5 | AB76: 98672.39 | AE76: 6107.1874 | AF76: Anurag Kochhar | AG76: GCC0954 | AH76: 104779.58 | AI76: 8906.2641 | AJ76: 29700 | AK76: 2524.5 | AL76: 145910.34 | AM76: RUS | AN76: RUS | AO76: 90373 | AP76: Randstad Professional US LP, | AQ76: Billable | AR76: 1 | AW76: VMS | AX76: GFKS | AY76: RGCC FSSC | AZ76: 90373 | BC76: Considered | CB76: Billed | CC76: US_SAP_L | CD76: 60002 | CE76: 30001312 | CF76: =A76 -> W0004109 | CG76: Fin | CH76: =SUM(O76,Q76,T76:X76,) -> 90085.585 | CI76: =SUM(AA76,AC76:AE76) -> 6107.1874 | CJ76: =SUM(Z76) -> 5687.5 | CK76: =AJ76 -> 29700 | CL76: =SUM(R76:S76) -> 2899.3057 | CM76: =SUM(AI76,AK76) -> 11430.764 | CO76: =SUM(CH76:CM76,-AL76) -> 0
A77: W0004110 | B77: GCC0947 | C77: Umesh M | D77: 43759 | F77: L09 | G77: Finance Capability Center | H77: Abhishek Khurana | I77: IN - Hyderabad_HQ | K77: Unique | L77: Active | M77: 0.085 | N77: 28 | O77: 83235.833 | R77: 1880.6691 | S77: 0 | T77: 195.58958 | U77: 75 | W77: 0 | X77: 4460.3751 | Y77: 89847.467 | Z77: 5687.5 | AB77: 95534.967 | AE77: 4292.2456 | AF77: Vaibhav Patel | AG77: GCC4027 | AH77: 99827.213 | AI77: 8485.3131 | AJ77: 29700 | AK77: 2524.5 | AL77: 140537.03 | AM77: RUS | AN77: RUS | AO77: 90242 | AP77: Randstad Professional US LP, | AQ77: Billable | AR77: 1 | AW77: Cash Application | AX77: GFKS | AY77: RGCC FSSC | AZ77: 90242 | BC77: Considered | CB77: Billed | CC77: US_SAP_L | CD77: 60002 | CE77: 30001312 | CF77: =A77 -> W0004110 | CG77: Fin | CH77: =SUM(O77,Q77,T77:X77,) -> 87966.798 | CI77: =SUM(AA77,AC77:AE77) -> 4292.2456 | CJ77: =SUM(Z77) -> 5687.5 | CK77: =AJ77 -> 29700 | CL77: =SUM(R77:S77) -> 1880.6691 | CM77: =SUM(AI77,AK77) -> 11009.813 | CO77: =SUM(CH77:CM77,-AL77) -> 0
A78: W0004936 | B78: GCC0948 | C78: Thakur Singh | D78: 43759 | F78: L09 | G78: Finance Capability Center | H78: Abhishek Khurana | I78: IN - Hyderabad_HQ | K78: Unique | L78: Active | M78: 0.085 | N78: 28 | O78: 77936.583 | R78: 1753.2853 | S78: 0 | T78: 182.34167 | U78: 75 | W78: 3892.9788 | X78: 4460.3751 | Y78: 88300.564 | Z78: 5687.5 | AB78: 93988.064 | AE78: 4292.2456 | AF78: Vaibhav Patel | AG78: GCC4027 | AH78: 98280.31 | AI78: 8353.8263 | AJ78: 29700 | AK78: 2524.5 | AL78: 138858.64 | AM78: RUS | AN78: RUS | AO78: 89158 | AP78: Randstad Professional US LP, | AQ78: Billable | AR78: 1 | AW78: COS and centralized setup | AX78: GFKS | AY78: RGCC FSSC | AZ78: 89158 | BC78: Considered | CB78: Billed | CC78: US_SAP_L | CD78: 60002 | CE78: 30001312 | CF78: =A78 -> W0004936 | CG78: Fin | CH78: =SUM(O78,Q78,T78:X78,) -> 86547.279 | CI78: =SUM(AA78,AC78:AE78) -> 4292.2456 | CJ78: =SUM(Z78) -> 5687.5 | CK78: =AJ78 -> 29700 | CL78: =SUM(R78:S78) -> 1753.2853 | CM78: =SUM(AI78,AK78) -> 10878.326 | CO78: =SUM(CH78:CM78,-AL78) -> 0
A79: W0004111 | B79: GCC0954 | C79: Anurag Kochhar | D79: 43761 | F79: L03 | G79: Finance Capability Center | H79: Abhishek Khurana | I79: IN - Hyderabad_HQ | K79: Managers | L79: Active | M79: 0.085 | N79: 28 | O79: 667959.58 | P79: 0.15 | Q79: 100193.94 | R79: 15936.53 | S79: 4272.4067 | T79: 1657.3992 | U79: 75 | W79: 61468.086 | X79: 5460.3751 | Y79: 857023.32 | Z79: 5687.5 | AA79: 29700 | AB79: 892410.82 | AE79: -892410.82 | AF79: Abhishek Khurana | AG79: 0 | AH79: 0 | AI79: 0 | AK79: 0 | AL79: 0 | AM79: RUS | AN79: Managers cost | AO79: 90217 | AP79: RGCC Hyd | AQ79: Non Billable -Managers | AR79: 1 | AW79: Leadership | AX79: GFKS | AY79: RGCC FSSC | AZ79: 90217 | BC79: Considered | CB79: Unbillled
A80: W0004112 | B80: GCC0957 | C80: Ashish Tyagi | D80: 43766 | F80: L08 | G80: Finance Capability Center | H80: Abhishek Khurana | I80: IN - Hyderabad_HQ | K80: Unique | L80: Active | M80: 0.085 | N80: 28 | O80: 99744.833 | R80: 2277.52 | S80: 0 | T80: 236.86208 | U80: 75 | W80: 0 | X80: 4460.3751 | Y80: 106794.59 | Z80: 5687.5 | AB80: 112482.09 | AE80: 4292.2456 | AF80: Vaibhav Patel | AG80: GCC4027 | AH80: 116774.34 | AI80: 9925.8186 | AJ80: 29700 | AK80: 2524.5 | AL80: 158924.65 | AM80: RUS | AN80: RUS | AO80: 90294 | AP80: Randstad Professional US LP, | AQ80: Billable | AR80: 1 | AW80: COS and centralized setup | AX80: GFKS | AY80: RGCC FSSC | AZ80: 90294 | BC80: Considered | CB80: Billed | CC80: US_SAP_L | CD80: 60002 | CE80: 30001312 | CF80: =A80 -> W0004112 | CG80: Fin | CH80: =SUM(O80,Q80,T80:X80,) -> 104517.07 | CI80: =SUM(AA80,AC80:AE80) -> 4292.2456 | CJ80: =SUM(Z80) -> 5687.5 | CK80: =AJ80 -> 29700 | CL80: =SUM(R80:S80) -> 2277.52 | CM80: =SUM(AI80,AK80) -> 12450.319 | CO80: =SUM(CH80:CM80,-AL80) -> 0
A81: W0004113 | B81: GCC0967 | C81: Vinay Kanth Vadapalli | D81: 43773 | F81: L08 | G81: Finance Capability Center | H81: Abhishek Khurana | I81: IN - Hyderabad_HQ | K81: Unique | L81: Active | M81: 0.085 | N81: 28 | O81: 143702.42 | R81: 3334.1947 | S81: 1036.4159 | T81: 346.75625 | U81: 75 | W81: 0 | X81: 4460.3751 | Y81: 152955.16 | Z81: 5687.5 | AB81: 158642.66 | AE81: 4292.2456 | AF81: Vaibhav Patel | AG81: GCC4027 | AH81: 162934.9 | AI81: 13849.467 | AJ81: 29700 | AK81: 2524.5 | AL81: 209008.87 | AM81: RUS | AN81: RUS | AO81: 89158 | AP81: Randstad Professional US LP, | AQ81: Billable | AR81: 1 | AW81: COS and centralized setup | AX81: GFKS | AY81: RGCC FSSC | AZ81: 89158 | BC81: Considered | CB81: Billed | CC81: US_SAP_L | CD81: 60002 | CE81: 30001312 | CF81: =A81 -> W0004113 | CG81: Fin | CH81: =SUM(O81,Q81,T81:X81,) -> 148584.55 | CI81: =SUM(AA81,AC81:AE81) -> 4292.2456 | CJ81: =SUM(Z81) -> 5687.5 | CK81: =AJ81 -> 29700 | CL81: =SUM(R81:S81) -> 4370.6106 | CM81: =SUM(AI81,AK81) -> 16373.967 | CO81: =SUM(CH81:CM81,-AL81) -> 0
A82: W0004114 | B82: GCC0972 | C82: Hemanth Shukla | D82: 43773 | F82: L09 | G82: HR Capability Center | H82: Shail Dasika | I82: IN - Hyderabad_HQ | K82: Unique | L82: Active | M82: 0.05 | N82: 28 | O82: 84943.167 | R82: 1921.7107 | S82: 42.192227 | T82: 199.85792 | U82: 75 | W82: 0 | X82: 4460.3751 | Y82: 91642.303 | Z82: 12402.5 | AB82: 104044.8 | AH82: 104044.8 | AI82: 5202.2401 | AJ82: 29700 | AK82: 1485 | AL82: 140432.04 | AM82: RUS | AN82: RUS | AO82: 90342 | AP82: Randstad Professional US LP, | AQ82: Billable | AR82: 1 | AW82: HR Support | AX82: HRCC | AY82: HRCC | AZ82: 90342 | BC82: Considered | CB82: Billed | CC82: US_SAP_L | CD82: 60002 | CE82: 30001312 | CF82: =A82 -> W0004114 | CG82: HR | CH82: =SUM(O82,Q82,T82:X82,) -> 89678.4 | CI82: =SUM(AA82,AC82:AE82) -> 0 | CJ82: =SUM(Z82) -> 12402.5 | CK82: =AJ82 -> 29700 | CL82: =SUM(R82:S82) -> 1963.903 | CM82: =SUM(AI82,AK82) -> 6687.2401 | CO82: =SUM(CH82:CM82,-AL82) -> 0
A83: W0004115 | B83: GCC0987 | C83: Akash Bhatt | D83: 43787 | E83: 46071 | F83: L10 | G83: Finance Capability Center | H83: Abhishek Khurana | I83: IN - Hyderabad_HQ | K83: Unique | L83: Exit emp | M83: 0.085 | N83: 18 | O83: 45009.804 | R83: 1562.8686 | S83: 902.99074 | T83: 162.53833 | U83: 75 | W83: 0 | X83: 4460.3751 | Y83: 52173.576 | Z83: 5687.5 | AB83: 57861.076 | AE83: 4292.2456 | AF83: Vaibhav Patel | AG83: GCC4027 | AH83: 62153.322 | AI83: 5283.0324 | AJ83: 29700 | AK83: 2524.5 | AL83: 99660.854 | AM83: RUS | AN83: RUS | AO83: 90242 | AP83: Randstad Professional US LP, | AQ83: Billable | AR83: 1 | AW83: AR | AX83: GFKS | AY83: RGCC FSSC | AZ83: 90242 | BC83: Considered | CB83: Billed | CC83: US_SAP_L | CD83: 60002 | CE83: 30001312 | CF83: =A83 -> W0004115 | CG83: Fin | CH83: =SUM(O83,Q83,T83:X83,) -> 49707.717 | CI83: =SUM(AA83,AC83:AE83) -> 4292.2456 | CJ83: =SUM(Z83) -> 5687.5 | CK83: =AJ83 -> 29700 | CL83: =SUM(R83:S83) -> 2465.8593 | CM83: =SUM(AI83,AK83) -> 7807.5324 | CO83: =SUM(CH83:CM83,-AL83) -> 0
A84: W0004116 | B84: GCC0989 | C84: Mujahed Mohammed | D84: 43787 | F84: L09 | G84: Finance Capability Center | H84: Abhishek Khurana | I84: IN - Hyderabad_HQ | K84: Unique | L84: Active | M84: 0.085 | N84: 28 | O84: 79302.833 | R84: 1786.1258 | S84: 1002.0563 | T84: 185.75708 | U84: 75 | W84: 0 | X84: 4460.3751 | Y84: 86812.148 | Z84: 5687.5 | AB84: 92499.648 | AE84: 6107.1874 | AF84: Anurag Kochhar | AG84: GCC0954 | AH84: 98606.835 | AI84: 8381.581 | AJ84: 29700 | AK84: 2524.5 | AL84: 139212.92 | AM84: RUS | AN84: RUS | AO84: 90129 | AP84: Randstad Professional US LP, | AQ84: Billable | AR84: 1 | AW84: Call Center | AX84: GFKS | AY84: RGCC FSSC | AZ84: 90129 | BC84: Considered | CB84: Billed | CC84: US_SAP_L | CD84: 60002 | CE84: 30001312 | CF84: =A84 -> W0004116 | CG84: Fin | CH84: =SUM(O84,Q84,T84:X84,) -> 84023.966 | CI84: =SUM(AA84,AC84:AE84) -> 6107.1874 | CJ84: =SUM(Z84) -> 5687.5 | CK84: =AJ84 -> 29700 | CL84: =SUM(R84:S84) -> 2788.1821 | CM84: =SUM(AI84,AK84) -> 10906.081 | CO84: =SUM(CH84:CM84,-AL84) -> 0
A85: W0004117 | B85: GCC0994 | C85: Syed Ali | D85: 43794 | F85: L08 | G85: Finance Capability Center | H85: Abhishek Khurana | I85: IN - Hyderabad_HQ | K85: Unique | L85: Active | M85: 0.085 | N85: 28 | O85: 99320.333 | R85: 2267.3157 | S85: 0 | T85: 235.80083 | U85: 75 | W85: 0 | X85: 4460.3751 | Y85: 106358.83 | Z85: 5687.5 | AB85: 112046.33 | AE85: 4292.2456 | AF85: Vaibhav Patel | AG85: GCC4027 | AH85: 116338.57 | AI85: 9888.7785 | AJ85: 29700 | AK85: 2524.5 | AL85: 158451.85 | AM85: RUS | AN85: RUS | AO85: 90220 | AP85: Randstad Professional US LP, | AQ85: Billable | AR85: 1 | AW85: Billing | AX85: GFKS | AY85: RGCC FSSC | AZ85: 90220 | BC85: Considered | CB85: Billed | CC85: US_SAP_L | CD85: 60002 | CE85: 30001312 | CF85: =A85 -> W0004117 | CG85: Fin | CH85: =SUM(O85,Q85,T85:X85,) -> 104091.51 | CI85: =SUM(AA85,AC85:AE85) -> 4292.2456 | CJ85: =SUM(Z85) -> 5687.5 | CK85: =AJ85 -> 29700 | CL85: =SUM(R85:S85) -> 2267.3157 | CM85: =SUM(AI85,AK85) -> 12413.278 | CO85: =SUM(CH85:CM85,-AL85) -> 0
A86: W0004118 | B86: GCC1009 | C86: Srikanth Kammari | D86: 43815 | F86: L06 | G86: Finance Capability Center | H86: Abhishek Khurana | I86: IN - Hyderabad_HQ | K86: Unique | L86: Active | M86: 0.085 | N86: 28 | O86: 174171.75 | R86: 4066.6306 | S86: 2257.9741 | T86: 422.92958 | U86: 75 | W86: 0 | X86: 4460.3751 | Y86: 185454.66 | Z86: 5687.5 | AB86: 191142.16 | AE86: 6107.1874 | AF86: Anurag Kochhar | AG86: GCC0954 | AH86: 197249.35 | AI86: 16766.194 | AJ86: 29700 | AK86: 2524.5 | AL86: 246240.04 | AM86: RUS | AN86: RUS | AO86: 90272 | AP86: Randstad Professional US LP, | AQ86: Billable | AR86: 1 | AW86: RPA | AX86: GFKS | AY86: RGCC FSSC | AZ86: 90272 | BC86: Considered | CB86: Billed | CC86: US_SAP_L | CD86: 60002 | CE86: 30001312 | CF86: =A86 -> W0004118 | CG86: Fin | CH86: =SUM(O86,Q86,T86:X86,) -> 179130.05 | CI86: =SUM(AA86,AC86:AE86) -> 6107.1874 | CJ86: =SUM(Z86) -> 5687.5 | CK86: =AJ86 -> 29700 | CL86: =SUM(R86:S86) -> 6324.6047 | CM86: =SUM(AI86,AK86) -> 19290.694 | CO86: =SUM(CH86:CM86,-AL86) -> 0
A87: W0004119 | B87: GCC1010 | C87: Devraj Ravindernath | D87: 43817 | F87: L04 | G87: Finance Capability Center | H87: Abhishek Khurana | I87: IN - Hyderabad_HQ | K87: Managers | L87: Active | M87: 0.085 | N87: 28 | O87: 342252.17 | P87: 0.15 | Q87: 51337.825 | R87: 8107.0232 | S87: 440.30144 | T87: 843.13042 | U87: 75 | W87: 0 | X87: 5460.3751 | Y87: 408515.82 | Z87: 5687.5 | AA87: 29700 | AB87: 443903.32 | AE87: -443903.32 | AF87: Abhishek Khurana | AG87: 0 | AH87: 0 | AI87: 0 | AK87: 0 | AL87: 0 | AM87: RUS | AN87: Managers cost | AO87: 90135 | AP87: RGCC Hyd | AQ87: Non Billable -Managers | AR87: 1 | AW87: Leadership | AX87: GFKS | AY87: RGCC FSSC | AZ87: 90135 | BC87: Considered | CB87: Unbillled
A88: W0004120 | B88: GCC1017 | C88: Ragini Mudliar | D88: 43836 | F88: L09 | G88: Finance Capability Center | H88: Abhishek Khurana | I88: IN - Hyderabad_HQ | K88: Unique | L88: Exit emp | M88: 0.085 | N88: 0 | O88: 0 | R88: 0 | S88: 0 | T88: 0 | U88: 0 | X88: 0 | Y88: 0 | Z88: 0 | AB88: 0 | AE88: 6107.1874 | AF88: Anurag Kochhar | AG88: GCC0954 | AH88: 0 | AI88: 0 | AJ88: 0 | AK88: 0 | AL88: 0 | AM88: RUS | AN88: RUS | AO88: 90366 | AP88: Randstad Professional US LP, | AQ88: Billable | AR88: 0 | AW88: Garnishment | AX88: GFKS | AY88: RGCC FSSC | AZ88: 90366 | BC88: #N/A | CA88: IJP to REPL | CB88: Unbillled
A89: W0005131 | B89: GCC1019 | C89: Sai Bangaru | D89: 43836 | F89: L09 | G89: Finance Capability Center | H89: Abhishek Khurana | I89: IN - Hyderabad_HQ | K89: Unique | L89: Active | M89: 0.085 | N89: 28 | O89: 80931.5 | R89: 1825.2764 | S89: 0 | T89: 189.82875 | U89: 75 | W89: 0 | X89: 4460.3751 | Y89: 87481.98 | Z89: 5687.5 | AB89: 93169.48 | AE89: 6107.1874 | AF89: Anurag Kochhar | AG89: GCC0954 | AH89: 99276.668 | AI89: 8438.5168 | AJ89: 29700 | AK89: 2524.5 | AL89: 139939.68 | AM89: RUS | AN89: RUS | AO89: 90366 | AP89: Randstad Professional US LP, | AQ89: Billable | AR89: 1 | AW89: AR | AX89: GFKS | AY89: RGCC FSSC | AZ89: 90366 | BC89: Considered | CB89: Billed | CC89: US_SAP_L | CD89: 60002 | CE89: 30001312 | CF89: =A89 -> W0005131 | CG89: Fin | CH89: =SUM(O89,Q89,T89:X89,) -> 85656.704 | CI89: =SUM(AA89,AC89:AE89) -> 6107.1874 | CJ89: =SUM(Z89) -> 5687.5 | CK89: =AJ89 -> 29700 | CL89: =SUM(R89:S89) -> 1825.2764 | CM89: =SUM(AI89,AK89) -> 10963.017 | CO89: =SUM(CH89:CM89,-AL89) -> 0
A90: W0005132 | B90: GCC1021 | C90: Mohammed Mohammed | D90: 43836 | F90: L09 | G90: Finance Capability Center | H90: Abhishek Khurana | I90: IN - Hyderabad_HQ | K90: Unique | L90: Active | M90: 0.085 | N90: 28 | O90: 61967.5 | R90: 1369.4111 | S90: 0 | T90: 142.41875 | U90: 75 | W90: 0 | X90: 4460.3751 | Y90: 68014.705 | Z90: 5687.5 | AB90: 73702.205 | AE90: 4292.2456 | AF90: Vaibhav Patel | AG90: GCC4027 | AH90: 77994.451 | AI90: 6629.5283 | AJ90: 29700 | AK90: 2524.5 | AL90: 116848.48 | AM90: RUS | AN90: RUS | AO90: 90382 | AP90: Randstad Professional US LP, | AQ90: Billable | AR90: 1 | AW90: VMS Reconciliations | AX90: GFKS | AY90: RGCC FSSC | AZ90: 90382 | BC90: Considered | CB90: Billed | CC90: US_SAP_L | CD90: 60002 | CE90: 30001312 | CF90: =A90 -> W0005132 | CG90: Fin | CH90: =SUM(O90,Q90,T90:X90,) -> 66645.294 | CI90: =SUM(AA90,AC90:AE90) -> 4292.2456 | CJ90: =SUM(Z90) -> 5687.5 | CK90: =AJ90 -> 29700 | CL90: =SUM(R90:S90) -> 1369.4111 | CM90: =SUM(AI90,AK90) -> 9154.0283 | CO90: =SUM(CH90:CM90,-AL90) -> 0
A91: W0004121 | B91: GCC1022 | C91: Aswin Ganta | D91: 43836 | F91: L08 | G91: Finance Capability Center | H91: Abhishek Khurana | I91: IN - Hyderabad_HQ | K91: Unique | L91: Active | M91: 0.085 | N91: 28 | O91: 87289.917 | R91: 1978.125 | S91: 1142.9167 | T91: 205.725 | U91: 75 | W91: 0 | X91: 4460.3751 | Y91: 95152.058 | Z91: 5687.5 | AB91: 100839.56 | AE91: 6107.1874 | AF91: Anurag Kochhar | AG91: GCC0954 | AH91: 106946.75 | AI91: 9090.4734 | AJ91: 29700 | AK91: 2524.5 | AL91: 148261.72 | AM91: RUS | AN91: RUS | AO91: 90129 | AP91: Randstad Professional US LP, | AQ91: Billable | AR91: 1 | AW91: Call Center | AX91: GFKS | AY91: RGCC FSSC | AZ91: 90129 | BC91: Considered | CB91: Billed | CC91: US_SAP_L | CD91: 60002 | CE91: 30001312 | CF91: =A91 -> W0004121 | CG91: Fin | CH91: =SUM(O91,Q91,T91:X91,) -> 92031.017 | CI91: =SUM(AA91,AC91:AE91) -> 6107.1874 | CJ91: =SUM(Z91) -> 5687.5 | CK91: =AJ91 -> 29700 | CL91: =SUM(R91:S91) -> 3121.0417 | CM91: =SUM(AI91,AK91) -> 11614.973 | CO91: =SUM(CH91:CM91,-AL91) -> 0
A92: W0005297 | B92: GCC1025 | C92: Devendra Mishra | D92: 43836 | F92: L08 | G92: Finance Capability Center | H92: Abhishek Khurana | I92: IN - Hyderabad_HQ | K92: Unique | L92: Active | M92: 0.085 | N92: 28 | O92: 96636.583 | R92: 2202.8045 | S92: 0 | T92: 229.09167 | U92: 75 | W92: 0 | X92: 4460.3751 | Y92: 103603.85 | Z92: 5687.5 | AB92: 109291.35 | AE92: 6107.1874 | AF92: Anurag Kochhar | AG92: GCC0954 | AH92: 115398.54 | AI92: 9808.8761 | AJ92: 29700 | AK92: 2524.5 | AL92: 157431.92 | AM92: RUS | AN92: RUS | AO92: 90373 | AP92: Randstad Professional US LP, | AQ92: Billable | AR92: 1 | AW92: VMS | AX92: GFKS | AY92: RGCC FSSC | AZ92: 90373 | BC92: Considered | CB92: Billed | CC92: US_SAP_L | CD92: 60002 | CE92: 30001312 | CF92: =A92 -> W0005297 | CG92: Fin | CH92: =SUM(O92,Q92,T92:X92,) -> 101401.05 | CI92: =SUM(AA92,AC92:AE92) -> 6107.1874 | CJ92: =SUM(Z92) -> 5687.5 | CK92: =AJ92 -> 29700 | CL92: =SUM(R92:S92) -> 2202.8045 | CM92: =SUM(AI92,AK92) -> 12333.376 | CO92: =SUM(CH92:CM92,-AL92) -> 0
A93: W0004122 | B93: GCC1053 | C93: Nikhil Jain | D93: 43857 | F93: L09 | G93: Finance Capability Center | H93: Abhishek Khurana | I93: IN - Hyderabad_HQ | K93: Unique | L93: Active | M93: 0.085 | N93: 28 | O93: 66622.583 | R93: 1481.3141 | S93: 21.396759 | T93: 154.05667 | U93: 75 | W93: 0 | X93: 4460.3751 | Y93: 72814.726 | Z93: 5687.5 | AB93: 78502.226 | AE93: 4292.2456 | AF93: Vaibhav Patel | AG93: GCC4027 | AH93: 82794.472 | AI93: 7037.5301 | AJ93: 29700 | AK93: 2524.5 | AL93: 122056.5 | AM93: RUS | AN93: RUS | AO93: 90382 | AP93: Randstad Professional US LP, | AQ93: Billable | AR93: 1 | AW93: VMS Reconciliations | AX93: GFKS | AY93: RGCC FSSC | AZ93: 90382 | BC93: Considered | CB93: Billed | CC93: US_SAP_L | CD93: 60002 | CE93: 30001312 | CF93: =A93 -> W0004122 | CG93: Fin | CH93: =SUM(O93,Q93,T93:X93,) -> 71312.015 | CI93: =SUM(AA93,AC93:AE93) -> 4292.2456 | CJ93: =SUM(Z93) -> 5687.5 | CK93: =AJ93 -> 29700 | CL93: =SUM(R93:S93) -> 1502.7109 | CM93: =SUM(AI93,AK93) -> 9562.0301 | CO93: =SUM(CH93:CM93,-AL93) -> 0
A94: W0004123 | B94: GCC1063 | C94: Apoorva Gosswamy | D94: 43864 | F94: L08 | G94: Finance Capability Center | H94: Abhishek Khurana | I94: IN - Hyderabad_HQ | K94: Unique | L94: Active | M94: 0.085 | N94: 28 | O94: 105866.25 | R94: 2424.6715 | S94: 0 | T94: 252.16583 | U94: 75 | W94: 0 | X94: 4460.3751 | Y94: 113078.46 | Z94: 5687.5 | AB94: 118765.96 | AE94: 6107.1874 | AF94: Anurag Kochhar | AG94: GCC0954 | AH94: 124873.15 | AI94: 10614.218 | AJ94: 29700 | AK94: 2524.5 | AL94: 167711.87 | AM94: RUS | AN94: RUS | AO94: 90271 | AP94: Randstad Professional US LP, | AQ94: Billable | AR94: 1 | AW94: Call Center | AX94: GFKS | AY94: RGCC FSSC | AZ94: 90271 | BC94: Considered | CB94: Billed | CC94: US_SAP_L | CD94: 60002 | CE94: 30001312 | CF94: =A94 -> W0004123 | CG94: Fin | CH94: =SUM(O94,Q94,T94:X94,) -> 110653.79 | CI94: =SUM(AA94,AC94:AE94) -> 6107.1874 | CJ94: =SUM(Z94) -> 5687.5 | CK94: =AJ94 -> 29700 | CL94: =SUM(R94:S94) -> 2424.6715 | CM94: =SUM(AI94,AK94) -> 13138.718 | CO94: =SUM(CH94:CM94,-AL94) -> 0
A95: W0004124 | B95: GCC1068 | C95: Rithwik Kommajosyula | D95: 43871 | F95: L09 | G95: Finance Capability Center | H95: Abhishek Khurana | I95: IN - Hyderabad_HQ | K95: Unique | L95: Active | M95: 0.085 | N95: 28 | O95: 89981.25 | R95: 2042.8205 | S95: 354.08889 | T95: 212.45333 | U95: 75 | W95: 4097.8724 | X95: 4460.3751 | Y95: 101223.86 | Z95: 5687.5 | AB95: 106911.36 | AE95: 6263.256 | AF95: Poojan Gandhi | AG95: GCC1254 | AH95: 113174.62 | AI95: 9619.8424 | AJ95: 29700 | AK95: 2524.5 | AL95: 155018.96 | AM95: RUS | AN95: RUS | AO95: 90349 | AP95: Randstad Professional US LP, | AQ95: Billable | AR95: 1 | AW95: Service Delivery | AX95: GFKS | AY95: RGCC FSSC | AZ95: 90349 | BC95: Considered | CB95: Billed | CC95: US_SAP_L | CD95: 60002 | CE95: 30001312 | CF95: =A95 -> W0004124 | CG95: Fin | CH95: =SUM(O95,Q95,T95:X95,) -> 98826.951 | CI95: =SUM(AA95,AC95:AE95) -> 6263.256 | CJ95: =SUM(Z95) -> 5687.5 | CK95: =AJ95 -> 29700 | CL95: =SUM(R95:S95) -> 2396.9094 | CM95: =SUM(AI95,AK95) -> 12144.342 | CO95: =SUM(CH95:CM95,-AL95) -> 0
A96: W0004125 | B96: GCC1070 | C96: Yaseer Sayeed | D96: 43871 | F96: L10 | G96: Talent Services Capability Center | H96: Ankur Sud | I96: IN - Hyderabad_HQ | K96: Unique | L96: Active | M96: 0.05 | N96: 28 | O96: 87080.083 | R96: 1973.0809 | S96: 1140.0023 | T96: 205.20042 | U96: 75 | W96: 0 | X96: 4460.3751 | Y96: 94933.742 | Z96: 4154.1667 | AB96: 99087.909 | AH96: 99087.909 | AI96: 4954.3954 | AJ96: 29700 | AK96: 1485 | AL96: 135227.3 | AM96: RUS | AN96: RUS | AO96: 35887 | AP96: Randstad Professional US LP, | AQ96: Billable | AR96: 1 | AW96: Recruiting(KR) | AX96: RD US | AY96: Digital US - TMT- AAMDP | AZ96: 35887 | BC96: Considered | CB96: Billed | CC96: US_SAP_L | CD96: 60002 | CE96: 30001312 | CF96: =A96 -> W0004125 | CG96: TS | CH96: =SUM(O96,Q96,T96:X96,) -> 91820.659 | CI96: =SUM(AA96,AC96:AE96) -> 0 | CJ96: =SUM(Z96) -> 4154.1667 | CK96: =AJ96 -> 29700 | CL96: =SUM(R96:S96) -> 3113.0832 | CM96: =SUM(AI96,AK96) -> 6439.3954 | CO96: =SUM(CH96:CM96,-AL96) -> 0
A97: W0004126 | B97: GCC1084 | C97: Anil Kumar Guduru | D97: 43885 | F97: L09 | G97: Finance Capability Center | H97: Abhishek Khurana | I97: IN - Hyderabad_HQ | K97: Unique | L97: Active | M97: 0.085 | N97: 28 | O97: 85926.167 | R97: 1945.3405 | S97: 477.68918 | T97: 202.31542 | U97: 75 | W97: 4097.8724 | X97: 4460.3751 | Y97: 97184.759 | Z97: 5687.5 | AB97: 102872.26 | AE97: 6263.256 | AF97: Poojan Gandhi | AG97: GCC1254 | AH97: 109135.52 | AI97: 9276.5188 | AJ97: 29700 | AK97: 2524.5 | AL97: 150636.53 | AM97: RUS | AN97: RUS | AO97: 90349 | AP97: Randstad Professional US LP, | AQ97: Billable | AR97: 1 | AW97: Service Delivery | AX97: GFKS | AY97: RGCC FSSC | AZ97: 90349 | BC97: Considered | CB97: Billed | CC97: US_SAP_L | CD97: 60002 | CE97: 30001312 | CF97: =A97 -> W0004126 | CG97: Fin | CH97: =SUM(O97,Q97,T97:X97,) -> 94761.73 | CI97: =SUM(AA97,AC97:AE97) -> 6263.256 | CJ97: =SUM(Z97) -> 5687.5 | CK97: =AJ97 -> 29700 | CL97: =SUM(R97:S97) -> 2423.0297 | CM97: =SUM(AI97,AK97) -> 11801.019 | CO97: =SUM(CH97:CM97,-AL97) -> 0
A98: W0004127 | B98: GCC1085 | C98: Abhinash Sharma | D98: 43892 | F98: L08 | G98: Finance Capability Center | H98: Abhishek Khurana | I98: IN - Hyderabad_HQ | K98: Unique | L98: Active | M98: 0.085 | N98: 28 | O98: 110390.5 | R98: 2533.4255 | S98: 0 | T98: 263.47625 | U98: 75 | W98: 8498.9873 | X98: 4460.3751 | Y98: 126221.76 | Z98: 5687.5 | AB98: 131909.26 | AE98: 6107.1874 | AF98: Anurag Kochhar | AG98: GCC0954 | AH98: 138016.45 | AI98: 11731.398 | AJ98: 29700 | AK98: 2524.5 | AL98: 181972.35 | AM98: RUS | AN98: RUS | AO98: 90362 | AP98: Randstad Professional US LP, | AQ98: Billable | AR98: 1 | AW98: Insurance and safety operations | AX98: GFKS | AY98: RGCC FSSC | AZ98: 90362 | BC98: Considered | CB98: Billed | CC98: US_SAP_L | CD98: 60002 | CE98: 30001312 | CF98: =A98 -> W0004127 | CG98: Fin | CH98: =SUM(O98,Q98,T98:X98,) -> 123688.34 | CI98: =SUM(AA98,AC98:AE98) -> 6107.1874 | CJ98: =SUM(Z98) -> 5687.5 | CK98: =AJ98 -> 29700 | CL98: =SUM(R98:S98) -> 2533.4255 | CM98: =SUM(AI98,AK98) -> 14255.898 | CO98: =SUM(CH98:CM98,-AL98) -> 0
A99: W0004128 | B99: GCC1086 | C99: Mahabali Adode | D99: 43892 | F99: L09 | G99: Finance Capability Center | H99: Abhishek Khurana | I99: IN - Hyderabad_HQ | K99: Unique | L99: Active | M99: 0.085 | N99: 28 | O99: 87869.083 | R99: 1992.0473 | S99: 1150.9606 | T99: 207.17292 | U99: 75 | W99: 0 | X99: 4460.3751 | Y99: 95754.639 | Z99: 5687.5 | AB99: 101442.14 | AE99: 6107.1874 | AF99: Anurag Kochhar | AG99: GCC0954 | AH99: 107549.33 | AI99: 9141.6928 | AJ99: 29700 | AK99: 2524.5 | AL99: 148915.52 | AM99: RUS | AN99: RUS | AO99: 90023 | AP99: Randstad Professional US LP, | AQ99: Billable | AR99: 1 | AW99: Insurance and safety operations | AX99: GFKS | AY99: RGCC FSSC | AZ99: 90023 | BC99: Considered | CB99: Billed | CC99: US_SAP_L | CD99: 60002 | CE99: 30001312 | CF99: =A99 -> W0004128 | CG99: Fin | CH99: =SUM(O99,Q99,T99:X99,) -> 92611.631 | CI99: =SUM(AA99,AC99:AE99) -> 6107.1874 | CJ99: =SUM(Z99) -> 5687.5 | CK99: =AJ99 -> 29700 | CL99: =SUM(R99:S99) -> 3143.0079 | CM99: =SUM(AI99,AK99) -> 11666.193 | CO99: =SUM(CH99:CM99,-AL99) -> 0
A100: W0005298 | B100: GCC1090 | C100: Santosh Pendyala | D100: 43892 | F100: L06 | G100: IT Capability Center | H100: Samy Mikkilineni | I100: IN - Hyderabad_HQ | K100: Unique | L100: Active | M100: 0.1 | N100: 28 | O100: 197184.33 | R100: 4740.008 | S100: 2738.6713 | T100: 492.96083 | U100: 75 | W100: 20200.462 | X100: 4460.3751 | Y100: 229891.81 | Z100: 7046.6667 | AB100: 236938.48 | AE100: 7875.5934 | AF100: Srikrishna Peesapati | AG100: GCC4569 | AH100: 244814.07 | AI100: 24481.407 | AJ100: 29700 | AK100: 2970 | AL100: 301965.48 | AM100: RUS | AN100: RUS | AO100: 90324 | AP100: Randstad Professional US LP, | AQ100: Billable | AR100: 1 | AW100: IT Dev/Prod support | AX100: RUS | AY100: RGCC RUS RBE | AZ100: 90324 | BC100: Considered | CB100: Billed | CC100: US_SAP_L | CD100: 60002 | CE100: 30001312 | CF100: =A100 -> W0005298 | CG100: IT | CH100: =SUM(O100,Q100,T100:X100,) -> 222413.13 | CI100: =SUM(AA100,AC100:AE100) -> 7875.5934 | CJ100: =SUM(Z100) -> 7046.6667 | CK100: =AJ100 -> 29700 | CL100: =SUM(R100:S100) -> 7478.6793 | CM100: =SUM(AI100,AK100) -> 27451.407 | CO100: =SUM(CH100:CM100,-AL100) -> 0
...
